{"C0":[{"date":"2016-12-29","basicStats":{"min":1.0,"max":1.0,"mean":1.0,"stDev":0.0}},{"date":"2016-12-26","basicStats":{"min":1.0,"max":1.0,"mean":1.0,"stDev":0.0}},{"date":"2016-12-19","basicStats":{"min":1.0,"max":1.0,"mean":1.0,"stDev":0.0}},{"date":"2016-12-16","basicStats":{"min":0.0,"max":0.0,"mean":0.0,"stDev":0.0}},{"date":"2016-12-09","basicStats":{"min":1.0,"max":1.0,"mean":1.0,"stDev":0.0}},{"date":"2016-12-06","basicStats":{"min":1.0,"max":1.0,"mean":1.0,"stDev":0.0}},{"date":"2016-11-26","basicStats":{"min":0.0,"max":0.0,"mean":0.0,"stDev":0.0}},{"date":"2016-11-19","basicStats":{"min":1.0,"max":1.0,"mean":1.0,"stDev":0.0}},{"date":"2016-11-16","basicStats":{"min":1.0,"max":1.0,"mean":1.0,"stDev":0.0}},{"date":"2016-11-09","basicStats":{"min":1.0,"max":1.0,"mean":1.0,"stDev":0.0}},{"date":"2016-11-06","basicStats":{"min":0.0,"max":0.0,"mean":0.0,"stDev":0.0}},{"date":"2016-10-27","basicStats":{"min":0.0,"max":0.0,"mean":0.0,"stDev":0.0}},{"date":"2016-10-20","basicStats":{"min":1.0,"max":1.0,"mean":1.0,"stDev":0.0}},{"date":"2016-10-17","basicStats":{"min":0.0,"max":0.0,"mean":0.0,"stDev":0.0}},{"date":"2016-10-07","basicStats":{"min":0.0,"max":0.0,"mean":0.0,"stDev":0.0}},{"date":"2016-09-30","basicStats":{"min":1.0,"max":1.0,"mean":1.0,"stDev":0.0}},{"date":"2016-09-27","basicStats":{"min":0.0,"max":0.0,"mean":0.0,"stDev":0.0}},{"date":"2016-09-17","basicStats":{"min":0.0,"max":0.0,"mean":0.0,"stDev":0.0}},{"date":"2016-09-10","basicStats":{"min":0.0,"max":0.0,"mean":0.0,"stDev":0.0}},{"date":"2016-09-07","basicStats":{"min":0.0,"max":0.0,"mean":0.0,"stDev":0.0}},{"date":"2016-08-28","basicStats":{"min":0.0,"max":0.0,"mean":0.0,"stDev":0.0}},{"date":"2016-08-21","basicStats":{"min":0.0,"max":0.0,"mean":0.0,"stDev":0.0}},{"date":"2016-08-18","basicStats":{"min":0.0,"max":0.0,"mean":0.0,"stDev":0.0}},{"date":"2016-08-08","basicStats":{"min":0.0,"max":0.0,"mean":0.0,"stDev":0.0}},{"date":"2016-08-01","basicStats":{"min":0.0,"max":0.0,"mean":0.0,"stDev":0.0}},{"date":"2016-07-29","basicStats":{"min":0.0,"max":0.0,"mean":0.0,"stDev":0.0}},{"date":"2016-07-19","basicStats":{"min":0.0,"max":0.0,"mean":0.0,"stDev":0.0}},{"date":"2016-07-12","basicStats":{"min":0.0,"max":0.0,"mean":0.0,"stDev":0.0}},{"date":"2016-07-09","basicStats":{"min":0.0,"max":0.0,"mean":0.0,"stDev":0.0}},{"date":"2016-06-29","basicStats":{"min":0.0,"max":0.0,"mean":0.0,"stDev":0.0}},{"date":"2016-06-22","basicStats":{"min":0.0,"max":0.0,"mean":0.0,"stDev":0.0}},{"date":"2016-06-19","basicStats":{"min":0.0,"max":0.0,"mean":0.0,"stDev":0.0}},{"date":"2016-06-09","basicStats":{"min":0.0,"max":0.0,"mean":0.0,"stDev":0.0}},{"date":"2016-06-02","basicStats":{"min":1.0,"max":1.0,"mean":1.0,"stDev":0.0}},{"date":"2016-05-20","basicStats":{"min":0.0,"max":0.0,"mean":0.0,"stDev":0.0}},{"date":"2016-05-13","basicStats":{"min":0.0,"max":0.0,"mean":0.0,"stDev":0.0}},{"date":"2016-04-23","basicStats":{"min":0.0,"max":0.0,"mean":0.0,"stDev":0.0}},{"date":"2016-04-10","basicStats":{"min":1.0,"max":1.0,"mean":1.0,"stDev":0.0}},{"date":"2016-03-24","basicStats":{"min":1.0,"max":1.0,"mean":1.0,"stDev":0.0}},{"date":"2016-03-04","basicStats":{"min":0.0,"max":0.0,"mean":0.0,"stDev":0.0}},{"date":"2016-02-10","basicStats":{"min":1.0,"max":1.0,"mean":1.0,"stDev":0.0}},{"date":"2016-01-24","basicStats":{"min":1.0,"max":1.0,"mean":1.0,"stDev":0.0}},{"date":"2016-01-14","basicStats":{"min":0.0,"max":0.0,"mean":0.0,"stDev":0.0}},{"date":"2016-01-11","basicStats":{"min":1.0,"max":1.0,"mean":1.0,"stDev":0.0}}],"C1":[{"date":"2016-12-29","basicStats":{"min":-0.014665498398244381,"max":0.03626258671283722,"mean":0.011942136077868534,"stDev":0.008673560735209347}},{"date":"2016-12-26","basicStats":{"min":-0.03695937246084213,"max":0.13364307582378387,"mean":0.06798386424551156,"stDev":0.027474352888474617}},{"date":"2016-12-19","basicStats":{"min":-0.009265858680009842,"max":0.08580183982849121,"mean":0.04855705246560083,"stDev":0.014228291716569853}},{"date":"2016-12-16","basicStats":{"min":-0.011689691804349422,"max":0.018374932929873466,"mean":0.004330990959219481,"stDev":0.0045695822802169165}},{"date":"2016-12-09","basicStats":{"min":0.001738888444378972,"max":0.01727103814482689,"mean":0.009509291650407843,"stDev":0.00275296077072062}},{"date":"2016-12-06","basicStats":{"min":-0.0046182069927453995,"max":0.030564868822693825,"mean":0.011734880572699998,"stDev":0.006342221178426468}},{"date":"2016-11-26","basicStats":{"min":-0.019234878942370415,"max":0.0612308643758297,"mean":0.030768423823684256,"stDev":0.010583192409820983}},{"date":"2016-11-19","basicStats":{"min":-0.03482586890459061,"max":0.03317811340093613,"mean":0.0014334336529425076,"stDev":0.012249846944628958}},{"date":"2016-11-16","basicStats":{"min":-0.03821062296628952,"max":0.0805961936712265,"mean":0.01786262987120859,"stDev":0.020027108003142193}},{"date":"2016-11-09","basicStats":{"min":0.007817589677870274,"max":0.049744896590709686,"mean":0.027466199803234413,"stDev":0.007414030307281713}},{"date":"2016-11-06","basicStats":{"min":0.09086307138204575,"max":0.22927941381931305,"mean":0.16971649041077108,"stDev":0.019738820640777026}},{"date":"2016-10-27","basicStats":{"min":0.09486552327871323,"max":0.21100467443466187,"mean":0.1575035522924053,"stDev":0.019079457275477878}},{"date":"2016-10-20","basicStats":{"min":0.07332344353199005,"max":0.13557873666286469,"mean":0.09968597990326863,"stDev":0.008564684496261602}},{"date":"2016-10-17","basicStats":{"min":0.21189215779304504,"max":0.5076335668563843,"mean":0.41188743424293245,"stDev":0.053544117578240596}},{"date":"2016-10-07","basicStats":{"min":0.19628770649433136,"max":0.4302048683166504,"mean":0.3508930197777631,"stDev":0.041691834767713015}},{"date":"2016-09-30","basicStats":{"min":-0.132821723818779,"max":0.20820352435112,"mean":0.05272155840582617,"stDev":0.05811247990476727}},{"date":"2016-09-27","basicStats":{"min":0.20321930944919586,"max":0.43478259444236755,"mean":0.33542545907789295,"stDev":0.039762268771699937}},{"date":"2016-09-17","basicStats":{"min":0.21658389270305634,"max":0.45363736152648926,"mean":0.3155244671441941,"stDev":0.04675575610520808}},{"date":"2016-09-10","basicStats":{"min":0.2178288996219635,"max":0.5402584671974182,"mean":0.34861958357901573,"stDev":0.06657027662560074}},{"date":"2016-09-07","basicStats":{"min":0.21229049563407898,"max":0.5696721076965332,"mean":0.36509487693828924,"stDev":0.07649806472695668}},{"date":"2016-08-28","basicStats":{"min":0.22997735440731049,"max":0.658823549747467,"mean":0.43586960006669134,"stDev":0.09544902988989826}},{"date":"2016-08-21","basicStats":{"min":0.20792078971862793,"max":0.7129356265068054,"mean":0.45607925287264933,"stDev":0.11120161763731903}},{"date":"2016-08-18","basicStats":{"min":0.21355655789375305,"max":0.700507640838623,"mean":0.4435066483871159,"stDev":0.11020772934004205}},{"date":"2016-08-08","basicStats":{"min":0.20610982179641724,"max":0.690270185470581,"mean":0.4326771461893742,"stDev":0.10870509355489545}},{"date":"2016-08-01","basicStats":{"min":0.1990480273962021,"max":0.6872740983963013,"mean":0.4449326882242628,"stDev":0.10811924039566372}},{"date":"2016-07-29","basicStats":{"min":0.1908799707889557,"max":0.641796350479126,"mean":0.41082301587303344,"stDev":0.09728891761264769}},{"date":"2016-07-19","basicStats":{"min":0.1589427888393402,"max":0.6272762417793274,"mean":0.3824890461856846,"stDev":0.09338070323248741}},{"date":"2016-07-12","basicStats":{"min":0.16628606617450714,"max":0.5706161260604858,"mean":0.35140162837470323,"stDev":0.07320741229597076}},{"date":"2016-07-09","basicStats":{"min":0.14860624074935913,"max":0.4931129515171051,"mean":0.3094721258538737,"stDev":0.058918455770545435}},{"date":"2016-06-29","basicStats":{"min":0.14144012331962585,"max":0.4028974175453186,"mean":0.22614165363816915,"stDev":0.03688180773867383}},{"date":"2016-06-22","basicStats":{"min":0.11647901684045792,"max":0.3966785669326782,"mean":0.19488113760795248,"stDev":0.040521113957014465}},{"date":"2016-06-19","basicStats":{"min":0.10724637657403946,"max":0.43295320868492126,"mean":0.16699446879239907,"stDev":0.04415562666820019}},{"date":"2016-06-09","basicStats":{"min":0.11251980811357498,"max":0.29056307673454285,"mean":0.15158658453927,"stDev":0.022800658417259024}},{"date":"2016-06-02","basicStats":{"min":-0.010115747340023518,"max":0.005164019297808409,"mean":-0.0025764457067935626,"stDev":0.002321525300974484}},{"date":"2016-05-20","basicStats":{"min":0.07590361684560776,"max":0.33291923999786377,"mean":0.10608975685958107,"stDev":0.03334534304360843}},{"date":"2016-05-13","basicStats":{"min":0.09524969756603241,"max":0.40550363063812256,"mean":0.1463513832998155,"stDev":0.04477665581555955}},{"date":"2016-04-23","basicStats":{"min":0.08661139756441116,"max":0.3529292643070221,"mean":0.12474414636858917,"stDev":0.040173600833353536}},{"date":"2016-04-10","basicStats":{"min":0.13305579125881195,"max":0.19137749075889587,"mean":0.15074567661738128,"stDev":0.007607073870277855}},{"date":"2016-03-24","basicStats":{"min":0.0080106807872653,"max":0.01957390084862709,"mean":0.0134261360431576,"stDev":0.0017926510976990218}},{"date":"2016-03-04","basicStats":{"min":0.058396369218826294,"max":0.2804025709629059,"mean":0.08055256480006977,"stDev":0.018437907240449844}},{"date":"2016-02-10","basicStats":{"min":-0.005111167673021555,"max":0.012323720380663872,"mean":0.0025696162905116363,"stDev":0.0028094213397063003}},{"date":"2016-01-24","basicStats":{"min":0.02972576953470707,"max":0.05136203020811081,"mean":0.04063577232800442,"stDev":0.003511932904511929}},{"date":"2016-01-14","basicStats":{"min":0.036764707416296005,"max":0.2963525950908661,"mean":0.07949884257435015,"stDev":0.026611817609008735}},{"date":"2016-01-11","basicStats":{"min":-0.02016412653028965,"max":0.06271472573280334,"mean":0.005139000042754159,"stDev":0.011846109655053288}}],"C2":[{"date":"2016-12-29","basicStats":{"min":0.1071522980928421,"max":0.24936319887638092,"mean":0.17777949441606697,"stDev":0.029792557357999596}},{"date":"2016-12-26","basicStats":{"min":-0.06198346987366676,"max":0.12835504114627838,"mean":0.03841389838020711,"stDev":0.036397831046305305}},{"date":"2016-12-19","basicStats":{"min":-0.08883827179670334,"max":0.09084167331457138,"mean":-0.013462340454533397,"stDev":0.030021596495347917}},{"date":"2016-12-16","basicStats":{"min":0.5088047385215759,"max":0.5542994141578674,"mean":0.53852145631642,"stDev":0.008257292253073346}},{"date":"2016-12-09","basicStats":{"min":0.5356122255325317,"max":0.5664821267127991,"mean":0.5522362415916414,"stDev":0.005868550886450076}},{"date":"2016-12-06","basicStats":{"min":0.49215593934059143,"max":0.556486189365387,"mean":0.5228414795746549,"stDev":0.017160207869466735}},{"date":"2016-11-26","basicStats":{"min":0.7278727293014526,"max":0.7938089370727539,"mean":0.7758104114675797,"stDev":0.010265221398836101}},{"date":"2016-11-19","basicStats":{"min":0.33441823720932007,"max":0.4172077775001526,"mean":0.37369443858561374,"stDev":0.01424893342482401}},{"date":"2016-11-16","basicStats":{"min":0.08533021807670593,"max":0.2643306851387024,"mean":0.17679008211164904,"stDev":0.04042112714331741}},{"date":"2016-11-09","basicStats":{"min":0.2965613901615143,"max":0.33909520506858826,"mean":0.31582450997794476,"stDev":0.00817113694272341}},{"date":"2016-11-06","basicStats":{"min":-0.08743897080421448,"max":0.0048828125,"mean":-0.0320186042633963,"stDev":0.013086051560986349}},{"date":"2016-10-27","basicStats":{"min":-0.11184345930814743,"max":0.004073319956660271,"mean":-0.05676099038143477,"stDev":0.01223256098473315}},{"date":"2016-10-20","basicStats":{"min":0.08147655427455902,"max":0.17717820405960083,"mean":0.12169143424814577,"stDev":0.011822294450023722}},{"date":"2016-10-17","basicStats":{"min":-0.023871615529060364,"max":0.2631373405456543,"mean":0.18288329988555857,"stDev":0.05067190904262098}},{"date":"2016-10-07","basicStats":{"min":-0.007586072664707899,"max":0.19469371438026428,"mean":0.13521928157823965,"stDev":0.034826177353417816}},{"date":"2016-09-30","basicStats":{"min":-0.28424975275993347,"max":0.13761916756629944,"mean":-0.05007612564278769,"stDev":0.0822853218551793}},{"date":"2016-09-27","basicStats":{"min":0.029264535754919052,"max":0.19090387225151062,"mean":0.12444479881766693,"stDev":0.028563426403953113}},{"date":"2016-09-17","basicStats":{"min":0.044300276786088943,"max":0.20830324292182922,"mean":0.11353411268213455,"stDev":0.03206897909065611}},{"date":"2016-09-10","basicStats":{"min":0.04224774241447449,"max":0.24556562304496765,"mean":0.12991995175431903,"stDev":0.04327518337241597}},{"date":"2016-09-07","basicStats":{"min":0.04483572393655777,"max":0.27592524886131287,"mean":0.13920073870493013,"stDev":0.049229238178521595}},{"date":"2016-08-28","basicStats":{"min":0.04094827547669411,"max":0.39670872688293457,"mean":0.2219579133049439,"stDev":0.07298697565955513}},{"date":"2016-08-21","basicStats":{"min":0.03913305327296257,"max":0.44087445735931396,"mean":0.23439601519011252,"stDev":0.08449447919360042}},{"date":"2016-08-18","basicStats":{"min":0.04390586540102959,"max":0.40735185146331787,"mean":0.21312291339269213,"stDev":0.08087837673303841}},{"date":"2016-08-08","basicStats":{"min":0.03487784415483475,"max":0.38766005635261536,"mean":0.19965944928048815,"stDev":0.07863905483150549}},{"date":"2016-08-01","basicStats":{"min":0.03132161870598793,"max":0.38013535737991333,"mean":0.20634580415037235,"stDev":0.0784473195633913}},{"date":"2016-07-29","basicStats":{"min":0.016630269587039948,"max":0.33466991782188416,"mean":0.17080007635652353,"stDev":0.07167543536314834}},{"date":"2016-07-19","basicStats":{"min":0.01329915039241314,"max":0.3013167977333069,"mean":0.1442979785212236,"stDev":0.05991522376155879}},{"date":"2016-07-12","basicStats":{"min":0.011653314344584942,"max":0.2736356556415558,"mean":0.12366852648296779,"stDev":0.04882787770146244}},{"date":"2016-07-09","basicStats":{"min":-0.009285942651331425,"max":0.21040868759155273,"mean":0.09059844931074294,"stDev":0.038997500627710395}},{"date":"2016-06-29","basicStats":{"min":-0.016905901953577995,"max":0.13658685982227325,"mean":0.02853512133920729,"stDev":0.023498602097428448}},{"date":"2016-06-22","basicStats":{"min":-0.04974619299173355,"max":0.13441705703735352,"mean":0.005710338513877523,"stDev":0.027495148369744458}},{"date":"2016-06-19","basicStats":{"min":-0.06842995434999466,"max":0.12994350492954254,"mean":-0.025210187508449135,"stDev":0.0283231074656716}},{"date":"2016-06-09","basicStats":{"min":-0.05037618428468704,"max":0.06088406965136528,"mean":-0.025678689930548056,"stDev":0.015042431424687525}},{"date":"2016-06-02","basicStats":{"min":0.6546408534049988,"max":0.7016803026199341,"mean":0.6707521533686391,"stDev":0.010630476420145198}},{"date":"2016-05-20","basicStats":{"min":-0.09899619221687317,"max":0.04879938066005707,"mean":-0.07009665085707929,"stDev":0.020882716709575158}},{"date":"2016-05-13","basicStats":{"min":-0.11727172881364822,"max":0.10647864639759064,"mean":-0.03926682640336696,"stDev":0.02835779663237722}},{"date":"2016-04-23","basicStats":{"min":-0.10144446045160294,"max":0.08291416615247726,"mean":-0.04969641298086032,"stDev":0.028262554885444935}},{"date":"2016-04-10","basicStats":{"min":0.2708371877670288,"max":0.3453705608844757,"mean":0.2924219239885503,"stDev":0.012538618965720347}},{"date":"2016-03-24","basicStats":{"min":0.4907836318016052,"max":0.5026131272315979,"mean":0.4953334488389778,"stDev":0.0019985107210292743}},{"date":"2016-03-04","basicStats":{"min":-0.0969313234090805,"max":0.04161928594112396,"mean":-0.06958949356015552,"stDev":0.013006512204968287}},{"date":"2016-02-10","basicStats":{"min":0.5126164555549622,"max":0.5482153296470642,"mean":0.5338857661157054,"stDev":0.007815951558141344}},{"date":"2016-01-24","basicStats":{"min":0.349245548248291,"max":0.3755546510219574,"mean":0.3599419943616887,"stDev":0.004072208161404675}},{"date":"2016-01-14","basicStats":{"min":-0.10109622776508331,"max":0.06525132805109024,"mean":-0.02825807252151332,"stDev":0.01568411128175546}},{"date":"2016-01-11","basicStats":{"min":0.36784830689430237,"max":0.5398244857788086,"mean":0.4275882911603471,"stDev":0.03822422574564789}}],"C3":[{"date":"2016-12-29","basicStats":{"min":0.6947000026702881,"max":0.9083999991416931,"mean":0.7908777866370518,"stDev":0.05032424721944412}},{"date":"2016-12-26","basicStats":{"min":0.19740000367164612,"max":0.2685999870300293,"mean":0.21614494139760138,"stDev":0.015158708327778556}},{"date":"2016-12-19","basicStats":{"min":0.19449999928474426,"max":0.26739999651908875,"mean":0.22572441344474406,"stDev":0.014916718617609284}},{"date":"2016-12-16","basicStats":{"min":0.48750001192092896,"max":0.5224000215530396,"mean":0.5049682550809607,"stDev":0.009543451093294495}},{"date":"2016-12-09","basicStats":{"min":0.7340999841690063,"max":0.7508000135421753,"mean":0.7427329174584324,"stDev":0.004474606863642892}},{"date":"2016-12-06","basicStats":{"min":0.7530999779701233,"max":0.8317000269889832,"mean":0.791465909119225,"stDev":0.017268878576635623}},{"date":"2016-11-26","basicStats":{"min":0.6097000241279602,"max":0.7578999996185303,"mean":0.6666778592594904,"stDev":0.022387375308434317}},{"date":"2016-11-19","basicStats":{"min":0.2207999974489212,"max":0.2353000044822693,"mean":0.22786913478960083,"stDev":0.003104108937980329}},{"date":"2016-11-16","basicStats":{"min":0.34310001134872437,"max":0.46560001373291016,"mean":0.4017134896121766,"stDev":0.03525174232780065}},{"date":"2016-11-09","basicStats":{"min":0.4399000108242035,"max":0.48809999227523804,"mean":0.46161260999892156,"stDev":0.013039441602199194}},{"date":"2016-11-06","basicStats":{"min":0.1501999944448471,"max":0.16359999775886536,"mean":0.154771774209752,"stDev":0.00301701476504576}},{"date":"2016-10-27","basicStats":{"min":0.16210000216960907,"max":0.17440000176429749,"mean":0.16562617264272908,"stDev":0.0023931806616742505}},{"date":"2016-10-20","basicStats":{"min":0.274399995803833,"max":0.2955999970436096,"mean":0.2866946481758199,"stDev":0.0032386860280922535}},{"date":"2016-10-17","basicStats":{"min":0.14560000598430634,"max":0.16459999978542328,"mean":0.15091429640951354,"stDev":0.0030691599513499464}},{"date":"2016-10-07","basicStats":{"min":0.15559999644756317,"max":0.1712000072002411,"mean":0.15960535183111943,"stDev":0.0026886192547736255}},{"date":"2016-09-30","basicStats":{"min":0.19280000030994415,"max":0.574400007724762,"mean":0.4135904692637788,"stDev":0.07831383272480442}},{"date":"2016-09-27","basicStats":{"min":0.15760000050067902,"max":0.1736000031232834,"mean":0.16177807917649115,"stDev":0.0025717582676476405}},{"date":"2016-09-17","basicStats":{"min":0.16030000150203705,"max":0.17560000717639923,"mean":0.16621568914819637,"stDev":0.0032356363553379796}},{"date":"2016-09-10","basicStats":{"min":0.1315000057220459,"max":0.15189999341964722,"mean":0.13833145166902944,"stDev":0.003558851527625364}},{"date":"2016-09-07","basicStats":{"min":0.14020000398159027,"max":0.163100004196167,"mean":0.15055073326852325,"stDev":0.004919206967326894}},{"date":"2016-08-28","basicStats":{"min":0.1429000049829483,"max":0.16509999334812164,"mean":0.15187587969201757,"stDev":0.004715623955093374}},{"date":"2016-08-21","basicStats":{"min":0.12399999797344208,"max":0.1485999971628189,"mean":0.13239912022331243,"stDev":0.005164332975845837}},{"date":"2016-08-18","basicStats":{"min":0.13850000500679016,"max":0.1670999974012375,"mean":0.14959692083233592,"stDev":0.006324108055459071}},{"date":"2016-08-08","basicStats":{"min":0.14030000567436218,"max":0.16990000009536743,"mean":0.1524636361780753,"stDev":0.00640522574362278}},{"date":"2016-08-01","basicStats":{"min":0.12700000405311584,"max":0.15240000188350677,"mean":0.13575703798195163,"stDev":0.004945370555653489}},{"date":"2016-07-29","basicStats":{"min":0.15139999985694885,"max":0.17299999296665192,"mean":0.16037837237862557,"stDev":0.004855601714233424}},{"date":"2016-07-19","basicStats":{"min":0.14429999887943268,"max":0.1720999926328659,"mean":0.15545733129917008,"stDev":0.005732388324749106}},{"date":"2016-07-12","basicStats":{"min":0.13279999792575836,"max":0.15150000154972076,"mean":0.14146275657756224,"stDev":0.0034424883113385878}},{"date":"2016-07-09","basicStats":{"min":0.15320000052452087,"max":0.17219999432563782,"mean":0.16169186205196212,"stDev":0.0042052072236773526}},{"date":"2016-06-29","basicStats":{"min":0.1623000055551529,"max":0.17710000276565552,"mean":0.17138196463502753,"stDev":0.0024882001735898928}},{"date":"2016-06-22","basicStats":{"min":0.13779999315738678,"max":0.15559999644756317,"mean":0.1483730938165421,"stDev":0.0025360049963604452}},{"date":"2016-06-19","basicStats":{"min":0.15919999778270721,"max":0.1777999997138977,"mean":0.1715873900877416,"stDev":0.002977607347436069}},{"date":"2016-06-09","basicStats":{"min":0.15960000455379486,"max":0.17659999430179596,"mean":0.17095982396969708,"stDev":0.0027676119474639898}},{"date":"2016-06-02","basicStats":{"min":1.0123000144958496,"max":1.0371999740600586,"mean":1.0200318897749314,"stDev":0.005353782147312954}},{"date":"2016-05-20","basicStats":{"min":0.15320000052452087,"max":0.17389999330043793,"mean":0.16748629024257747,"stDev":0.002987767390448866}},{"date":"2016-05-13","basicStats":{"min":0.12520000338554382,"max":0.15230000019073486,"mean":0.14477851904950548,"stDev":0.0045989432806232055}},{"date":"2016-04-23","basicStats":{"min":0.14079999923706055,"max":0.17990000545978546,"mean":0.1688230201995268,"stDev":0.0074679399480522875}},{"date":"2016-04-10","basicStats":{"min":0.26809999346733093,"max":0.28529998660087585,"mean":0.27884611493943445,"stDev":0.003004955606986934}},{"date":"2016-03-24","basicStats":{"min":0.7526000142097473,"max":0.7627000212669373,"mean":0.7581978007233376,"stDev":0.0019242720746826525}},{"date":"2016-03-04","basicStats":{"min":0.1581999957561493,"max":0.164900004863739,"mean":0.16240623201137058,"stDev":0.001152142338796855}},{"date":"2016-02-10","basicStats":{"min":0.79830002784729,"max":0.8198999762535095,"mean":0.8077173761346126,"stDev":0.004704152906309531}},{"date":"2016-01-24","basicStats":{"min":0.4715000092983246,"max":0.48590001463890076,"mean":0.47700938460064807,"stDev":0.0029398439679791714}},{"date":"2016-01-14","basicStats":{"min":0.13120000064373016,"max":0.1429000049829483,"mean":0.13383768331751067,"stDev":0.0016172512701040998}},{"date":"2016-01-11","basicStats":{"min":0.7937999963760376,"max":0.9214000105857849,"mean":0.8713524919713352,"stDev":0.0314363196755869}}],"C4":[{"date":"2016-12-29","basicStats":{"min":0.6969000101089478,"max":0.9761000275611877,"mean":0.8243735334740354,"stDev":0.06469359128105527}},{"date":"2016-12-26","basicStats":{"min":0.16680000722408295,"max":0.2353000044822693,"mean":0.19004912025505472,"stDev":0.015064072962207178}},{"date":"2016-12-19","basicStats":{"min":0.14010000228881836,"max":0.25130000710487366,"mean":0.19183863653552835,"stDev":0.02121034246130763}},{"date":"2016-12-16","basicStats":{"min":0.46160000562667847,"max":0.5024999976158142,"mean":0.48150205264780194,"stDev":0.009449923575353769}},{"date":"2016-12-09","basicStats":{"min":0.707099974155426,"max":0.7369999885559082,"mean":0.7230593108099584,"stDev":0.006602958750102456}},{"date":"2016-12-06","basicStats":{"min":0.7455999851226807,"max":0.8032000064849854,"mean":0.778680791340966,"stDev":0.00984223195779724}},{"date":"2016-11-26","basicStats":{"min":0.4690999984741211,"max":0.7628999948501587,"mean":0.6365703073414882,"stDev":0.042711686615535475}},{"date":"2016-11-19","basicStats":{"min":0.195700004696846,"max":0.21719999611377716,"mean":0.2024892962857248,"stDev":0.003038400824511861}},{"date":"2016-11-16","basicStats":{"min":0.29899999499320984,"max":0.43619999289512634,"mean":0.35383108472369595,"stDev":0.030502974340788015}},{"date":"2016-11-09","basicStats":{"min":0.41929998993873596,"max":0.4832000136375427,"mean":0.44761950120635724,"stDev":0.010457773767531122}},{"date":"2016-11-06","basicStats":{"min":0.11890000104904175,"max":0.1453000009059906,"mean":0.12800373924661249,"stDev":0.00456850202974531}},{"date":"2016-10-27","basicStats":{"min":0.13349999487400055,"max":0.15610000491142273,"mean":0.1412620969182237,"stDev":0.003914475163071212}},{"date":"2016-10-20","basicStats":{"min":0.2583000063896179,"max":0.2793000042438507,"mean":0.2684211876254279,"stDev":0.003934047293147593}},{"date":"2016-10-17","basicStats":{"min":0.11500000208616257,"max":0.1437000036239624,"mean":0.12468834312583521,"stDev":0.004455839492086587}},{"date":"2016-10-07","basicStats":{"min":0.125,"max":0.15440000593662262,"mean":0.136616862458218,"stDev":0.004414009988862092}},{"date":"2016-09-30","basicStats":{"min":0.15770000219345093,"max":0.5881999731063843,"mean":0.3610038852696018,"stDev":0.11294330199602061}},{"date":"2016-09-27","basicStats":{"min":0.1289999932050705,"max":0.15700000524520874,"mean":0.14122441367319974,"stDev":0.0044335909545286985}},{"date":"2016-09-17","basicStats":{"min":0.13369999825954437,"max":0.15929999947547913,"mean":0.14765513208735706,"stDev":0.005402663786788372}},{"date":"2016-09-10","basicStats":{"min":0.10589999705553055,"max":0.14169999957084656,"mean":0.12396810847249898,"stDev":0.006560367312012094}},{"date":"2016-09-07","basicStats":{"min":0.11110000312328339,"max":0.15039999783039093,"mean":0.13185542542760487,"stDev":0.00858692720823137}},{"date":"2016-08-28","basicStats":{"min":0.11410000175237656,"max":0.1551000028848648,"mean":0.13127947217973268,"stDev":0.00847976844956726}},{"date":"2016-08-21","basicStats":{"min":0.09790000319480896,"max":0.13860000669956207,"mean":0.1168748534440207,"stDev":0.00889210130906961}},{"date":"2016-08-18","basicStats":{"min":0.10899999737739563,"max":0.15399999916553497,"mean":0.13112793243394547,"stDev":0.010716403610248688}},{"date":"2016-08-08","basicStats":{"min":0.11069999635219574,"max":0.15970000624656677,"mean":0.13491261011956382,"stDev":0.01110650997811887}},{"date":"2016-08-01","basicStats":{"min":0.10239999741315842,"max":0.14489999413490295,"mean":0.12142565997748962,"stDev":0.00898197480931827}},{"date":"2016-07-29","basicStats":{"min":0.12280000001192093,"max":0.1664000004529953,"mean":0.1430288854920881,"stDev":0.009207552235229462}},{"date":"2016-07-19","basicStats":{"min":0.1103999987244606,"max":0.17090000212192535,"mean":0.14243108497883394,"stDev":0.010967404488570419}},{"date":"2016-07-12","basicStats":{"min":0.1054999977350235,"max":0.15139999985694885,"mean":0.12983511730242017,"stDev":0.007822292704025667}},{"date":"2016-07-09","basicStats":{"min":0.12620000541210175,"max":0.17149999737739563,"mean":0.14752287413280368,"stDev":0.00883544104787159}},{"date":"2016-06-29","basicStats":{"min":0.14020000398159027,"max":0.17589999735355377,"mean":0.16211290317765056,"stDev":0.004935636519353199}},{"date":"2016-06-22","basicStats":{"min":0.11829999834299088,"max":0.15620000660419464,"mean":0.14178460422368008,"stDev":0.005548124232911373}},{"date":"2016-06-19","basicStats":{"min":0.13600000739097595,"max":0.17790000140666962,"mean":0.16553739011506155,"stDev":0.005488147227930097}},{"date":"2016-06-09","basicStats":{"min":0.14550000429153442,"max":0.1729000061750412,"mean":0.16342837247680694,"stDev":0.003272509524953971}},{"date":"2016-06-02","basicStats":{"min":0.9908999800682068,"max":1.027999997138977,"mean":1.0115115101124201,"stDev":0.00716898229398854}},{"date":"2016-05-20","basicStats":{"min":0.13670000433921814,"max":0.18780000507831573,"mean":0.16338841635679238,"stDev":0.005352074933368995}},{"date":"2016-05-13","basicStats":{"min":0.1103999987244606,"max":0.149399995803833,"mean":0.13743717033863947,"stDev":0.00630217949566447}},{"date":"2016-04-23","basicStats":{"min":0.13099999725818634,"max":0.18559999763965607,"mean":0.16959860707876287,"stDev":0.00884371766403734}},{"date":"2016-04-10","basicStats":{"min":0.23970000445842743,"max":0.2637999951839447,"mean":0.2556890029558515,"stDev":0.004627146057754083}},{"date":"2016-03-24","basicStats":{"min":0.7390999794006348,"max":0.755299985408783,"mean":0.7461966276168838,"stDev":0.002309804044204753}},{"date":"2016-03-04","basicStats":{"min":0.13770000636577606,"max":0.14990000426769257,"mean":0.14445278614409882,"stDev":0.0017597944152879827}},{"date":"2016-02-10","basicStats":{"min":0.7793999910354614,"max":0.8065000176429749,"mean":0.7929398093230563,"stDev":0.0050024879198487}},{"date":"2016-01-24","basicStats":{"min":0.44830000400543213,"max":0.4691999852657318,"mean":0.459151539547352,"stDev":0.003581658056545928}},{"date":"2016-01-14","basicStats":{"min":0.10189999639987946,"max":0.11410000175237656,"mean":0.10743218475728801,"stDev":0.0017084140265659364}},{"date":"2016-01-11","basicStats":{"min":0.792900025844574,"max":0.8981000185012817,"mean":0.8298739738041356,"stDev":0.023195466674813914}}],"C5":[{"date":"2016-12-29","basicStats":{"min":0.6452000141143799,"max":0.9524999856948853,"mean":0.7792232390984766,"stDev":0.07087772627784905}},{"date":"2016-12-26","basicStats":{"min":0.1453000009059906,"max":0.21119999885559082,"mean":0.16576744868390025,"stDev":0.014112054737332303}},{"date":"2016-12-19","basicStats":{"min":0.10369999706745148,"max":0.21879999339580536,"mean":0.15825887089950227,"stDev":0.02176879980225914}},{"date":"2016-12-16","basicStats":{"min":0.4203999936580658,"max":0.4641000032424927,"mean":0.4423263200566907,"stDev":0.009885826699867886}},{"date":"2016-12-09","basicStats":{"min":0.6485999822616577,"max":0.6758999824523926,"mean":0.6637644433031343,"stDev":0.006149150709419099}},{"date":"2016-12-06","basicStats":{"min":0.7109000086784363,"max":0.7569000124931335,"mean":0.7320139298428538,"stDev":0.009866790718013748}},{"date":"2016-11-26","basicStats":{"min":0.42419999837875366,"max":0.7120000123977661,"mean":0.5890949415671171,"stDev":0.04238998744637187}},{"date":"2016-11-19","basicStats":{"min":0.16519999504089355,"max":0.18150000274181366,"mean":0.17199398803352614,"stDev":0.0024896693121024085}},{"date":"2016-11-16","basicStats":{"min":0.2782000005245209,"max":0.40880000591278076,"mean":0.3276114363955263,"stDev":0.03182882348691525}},{"date":"2016-11-09","basicStats":{"min":0.3865000009536743,"max":0.4569999873638153,"mean":0.41892236069150596,"stDev":0.011645473203662382}},{"date":"2016-11-06","basicStats":{"min":0.10740000009536743,"max":0.1476999968290329,"mean":0.11972023442911975,"stDev":0.006447928107795578}},{"date":"2016-10-27","basicStats":{"min":0.12319999933242798,"max":0.1543000042438507,"mean":0.13413658358506284,"stDev":0.005664798753919799}},{"date":"2016-10-20","basicStats":{"min":0.24089999496936798,"max":0.2606000006198883,"mean":0.2510478735035639,"stDev":0.0038257467303456486}},{"date":"2016-10-17","basicStats":{"min":0.10610000044107437,"max":0.14169999957084656,"mean":0.11904017583540805,"stDev":0.0060582169580073114}},{"date":"2016-10-07","basicStats":{"min":0.11890000104904175,"max":0.15620000660419464,"mean":0.13359655421281885,"stDev":0.006114594556130465}},{"date":"2016-09-30","basicStats":{"min":0.15160000324249268,"max":0.6151999831199646,"mean":0.38007294715455936,"stDev":0.11443069860488815}},{"date":"2016-09-27","basicStats":{"min":0.1257999986410141,"max":0.16050000488758087,"mean":0.140907844512169,"stDev":0.005937811123403245}},{"date":"2016-09-17","basicStats":{"min":0.131400004029274,"max":0.1647000014781952,"mean":0.14899501466681173,"stDev":0.006829327308044884}},{"date":"2016-09-10","basicStats":{"min":0.10339999943971634,"max":0.14659999310970306,"mean":0.124956524906314,"stDev":0.008404900557687542}},{"date":"2016-09-07","basicStats":{"min":0.11029999703168869,"max":0.16179999709129333,"mean":0.13556268336005567,"stDev":0.010676757969041974}},{"date":"2016-08-28","basicStats":{"min":0.11620000004768372,"max":0.163100004196167,"mean":0.1347103374204499,"stDev":0.009931397693069537}},{"date":"2016-08-21","basicStats":{"min":0.10080000013113022,"max":0.14710000157356262,"mean":0.12063673015170452,"stDev":0.010542880345209407}},{"date":"2016-08-18","basicStats":{"min":0.11490000039339066,"max":0.16899999976158142,"mean":0.13889890027579296,"stDev":0.012382056171501434}},{"date":"2016-08-08","basicStats":{"min":0.11860000342130661,"max":0.17100000381469727,"mean":0.14431209675421477,"stDev":0.012638844412209528}},{"date":"2016-08-01","basicStats":{"min":0.10580000281333923,"max":0.15459999442100525,"mean":0.12863027865389381,"stDev":0.010228731747106536}},{"date":"2016-07-29","basicStats":{"min":0.12929999828338623,"max":0.18140000104904175,"mean":0.15211759531690242,"stDev":0.010435297683608622}},{"date":"2016-07-19","basicStats":{"min":0.12330000102519989,"max":0.18960000574588776,"mean":0.1586464077638473,"stDev":0.011923978594007841}},{"date":"2016-07-12","basicStats":{"min":0.10930000245571136,"max":0.16609999537467957,"mean":0.14002272730851634,"stDev":0.009491831324705062}},{"date":"2016-07-09","basicStats":{"min":0.13359999656677246,"max":0.1873999983072281,"mean":0.15968328434700826,"stDev":0.011298541428120038}},{"date":"2016-06-29","basicStats":{"min":0.14900000393390656,"max":0.1932000070810318,"mean":0.17771392953623041,"stDev":0.005600818911873365}},{"date":"2016-06-22","basicStats":{"min":0.12759999930858612,"max":0.17219999432563782,"mean":0.1562953079528998,"stDev":0.006912789864293811}},{"date":"2016-06-19","basicStats":{"min":0.14810000360012054,"max":0.1995999962091446,"mean":0.1853006597488155,"stDev":0.0062668557943414095}},{"date":"2016-06-09","basicStats":{"min":0.16439999639987946,"max":0.19009999930858612,"mean":0.17939310833331096,"stDev":0.003815839023774129}},{"date":"2016-06-02","basicStats":{"min":0.9491000175476074,"max":0.9896000027656555,"mean":0.9707911280680261,"stDev":0.0062610672207245865}},{"date":"2016-05-20","basicStats":{"min":0.1467999964952469,"max":0.21289999783039093,"mean":0.18071539585322946,"stDev":0.007013845789869996}},{"date":"2016-05-13","basicStats":{"min":0.11749999970197678,"max":0.1678999960422516,"mean":0.15014904697051495,"stDev":0.008082920115338756}},{"date":"2016-04-23","basicStats":{"min":0.14249999821186066,"max":0.21160000562667847,"mean":0.1923148826507529,"stDev":0.010839039898373001}},{"date":"2016-04-10","basicStats":{"min":0.22390000522136688,"max":0.2526000142097473,"mean":0.24292074764404128,"stDev":0.005372004542633342}},{"date":"2016-03-24","basicStats":{"min":0.6931999921798706,"max":0.7063000202178955,"mean":0.699767448947576,"stDev":0.0020608383337448236}},{"date":"2016-03-04","basicStats":{"min":0.13369999825954437,"max":0.1468999981880188,"mean":0.13922001479352006,"stDev":0.002199070660514691}},{"date":"2016-02-10","basicStats":{"min":0.7088000178337097,"max":0.7354000210762024,"mean":0.721265689019233,"stDev":0.005034305730587742}},{"date":"2016-01-24","basicStats":{"min":0.42100000381469727,"max":0.438400000333786,"mean":0.4300917149944735,"stDev":0.0031851304109005055}},{"date":"2016-01-14","basicStats":{"min":0.08429999649524689,"max":0.09929999709129333,"mean":0.08977228746670263,"stDev":0.002122797663708543}},{"date":"2016-01-11","basicStats":{"min":0.7329000234603882,"max":0.8381999731063843,"mean":0.7762906891771767,"stDev":0.02618212603152075}}],"C6":[{"date":"2016-12-29","basicStats":{"min":0.6855000257492065,"max":1.0670000314712524,"mean":0.8457912756812893,"stDev":0.0870140715787922}},{"date":"2016-12-26","basicStats":{"min":0.1509999930858612,"max":0.23520000278949738,"mean":0.17315887091708693,"stDev":0.015444804025280395}},{"date":"2016-12-19","basicStats":{"min":0.09570000320672989,"max":0.23340000212192535,"mean":0.16121466297252054,"stDev":0.02642006240039021}},{"date":"2016-12-16","basicStats":{"min":0.4357999861240387,"max":0.48730000853538513,"mean":0.45990036685795344,"stDev":0.011654274429466862}},{"date":"2016-12-09","basicStats":{"min":0.6937000155448914,"max":0.7245000004768372,"mean":0.7098951613710779,"stDev":0.006203205452686653}},{"date":"2016-12-06","basicStats":{"min":0.7493000030517578,"max":0.8015999794006348,"mean":0.7735774918647805,"stDev":0.01176302468414749}},{"date":"2016-11-26","basicStats":{"min":0.450300008058548,"max":0.7721999883651733,"mean":0.6408589444726797,"stDev":0.04675223715121329}},{"date":"2016-11-19","basicStats":{"min":0.15889999270439148,"max":0.18050000071525574,"mean":0.17130139271272574,"stDev":0.002992981579652933}},{"date":"2016-11-16","basicStats":{"min":0.2919999957084656,"max":0.4332999885082245,"mean":0.3488889297475913,"stDev":0.037289307826159405}},{"date":"2016-11-09","basicStats":{"min":0.420199990272522,"max":0.48840001225471497,"mean":0.4496236800098698,"stDev":0.013500448189953058}},{"date":"2016-11-06","basicStats":{"min":0.12720000743865967,"max":0.18359999358654022,"mean":0.14540425231379853,"stDev":0.009130198538425817}},{"date":"2016-10-27","basicStats":{"min":0.14020000398159027,"max":0.18729999661445618,"mean":0.15599024919601817,"stDev":0.008565022183854574}},{"date":"2016-10-20","basicStats":{"min":0.25279998779296875,"max":0.2825999855995178,"mean":0.2705438415850364,"stDev":0.004428693859882621}},{"date":"2016-10-17","basicStats":{"min":0.09799999743700027,"max":0.16220000386238098,"mean":0.12065271265761049,"stDev":0.011696205297961245}},{"date":"2016-10-07","basicStats":{"min":0.1168999969959259,"max":0.18289999663829803,"mean":0.14093064529346086,"stDev":0.01103271062948273}},{"date":"2016-09-30","basicStats":{"min":0.15160000324249268,"max":0.6798999905586243,"mean":0.4325781524880541,"stDev":0.12459202638294717}},{"date":"2016-09-27","basicStats":{"min":0.1216999962925911,"max":0.1826000064611435,"mean":0.1498253665471182,"stDev":0.0109084514150497}},{"date":"2016-09-17","basicStats":{"min":0.1257999986410141,"max":0.1906999945640564,"mean":0.15931620242352715,"stDev":0.012730470036484285}},{"date":"2016-09-10","basicStats":{"min":0.0925000011920929,"max":0.1703999936580658,"mean":0.13399391505550426,"stDev":0.015264171534107557}},{"date":"2016-09-07","basicStats":{"min":0.09449999779462814,"max":0.1859000027179718,"mean":0.14519721395786717,"stDev":0.020349219929240506}},{"date":"2016-08-28","basicStats":{"min":0.08980000019073486,"max":0.18700000643730164,"mean":0.13348255150806732,"stDev":0.021216399142531494}},{"date":"2016-08-21","basicStats":{"min":0.07289999723434448,"max":0.17319999635219574,"mean":0.1193590174562945,"stDev":0.022655488490749463}},{"date":"2016-08-18","basicStats":{"min":0.08259999752044678,"max":0.19740000367164612,"mean":0.1392480204881459,"stDev":0.026582266484380095}},{"date":"2016-08-08","basicStats":{"min":0.0877000018954277,"max":0.20559999346733093,"mean":0.14568057188168826,"stDev":0.027256915996904624}},{"date":"2016-08-01","basicStats":{"min":0.08129999786615372,"max":0.1851000040769577,"mean":0.12813665698722138,"stDev":0.02313363182818726}},{"date":"2016-07-29","basicStats":{"min":0.10130000114440918,"max":0.21469999849796295,"mean":0.15339472146480865,"stDev":0.02386549550748983}},{"date":"2016-07-19","basicStats":{"min":0.09619999676942825,"max":0.23229999840259552,"mean":0.16687815270968379,"stDev":0.025685352117317435}},{"date":"2016-07-12","basicStats":{"min":0.08900000154972076,"max":0.20080000162124634,"mean":0.14796495593843925,"stDev":0.018891579788831207}},{"date":"2016-07-09","basicStats":{"min":0.12720000743865967,"max":0.2305999994277954,"mean":0.17203218493162725,"stDev":0.019660571052691894}},{"date":"2016-06-29","basicStats":{"min":0.1525000035762787,"max":0.2337000072002411,"mean":0.20426092386420514,"stDev":0.010995285724308251}},{"date":"2016-06-22","basicStats":{"min":0.1316000074148178,"max":0.2160000056028366,"mean":0.18631810870819096,"stDev":0.012024353004428681}},{"date":"2016-06-19","basicStats":{"min":0.14419999718666077,"max":0.24709999561309814,"mean":0.22470219941301722,"stDev":0.013135375594616918}},{"date":"2016-06-09","basicStats":{"min":0.1777999997138977,"max":0.23229999840259552,"mean":0.21501466271377373,"stDev":0.006608516869339034}},{"date":"2016-06-02","basicStats":{"min":0.9998000264167786,"max":1.0405999422073364,"mean":1.0201354838274093,"stDev":0.0065272163253242785}},{"date":"2016-05-20","basicStats":{"min":0.16110000014305115,"max":0.26420000195503235,"mean":0.2229661290531109,"stDev":0.010602327787756348}},{"date":"2016-05-13","basicStats":{"min":0.11389999836683273,"max":0.2069000005722046,"mean":0.17890263926183197,"stDev":0.01494126380658547}},{"date":"2016-04-23","basicStats":{"min":0.1518000066280365,"max":0.26179999113082886,"mean":0.23657661287490944,"stDev":0.018909611323704407}},{"date":"2016-04-10","basicStats":{"min":0.22059999406337738,"max":0.2619999945163727,"mean":0.24891759515289322,"stDev":0.0073635243986985045}},{"date":"2016-03-24","basicStats":{"min":0.7318000197410583,"max":0.7459999918937683,"mean":0.7393951617902342,"stDev":0.0021458824580496837}},{"date":"2016-03-04","basicStats":{"min":0.12870000302791595,"max":0.16500000655651093,"mean":0.15451319640245612,"stDev":0.003703353226770577}},{"date":"2016-02-10","basicStats":{"min":0.7641000151634216,"max":0.7932000160217285,"mean":0.778689662950478,"stDev":0.005780897085048311}},{"date":"2016-01-24","basicStats":{"min":0.4503999948501587,"max":0.4702000021934509,"mean":0.4610257330528104,"stDev":0.003431660843057521}},{"date":"2016-01-14","basicStats":{"min":0.08500000089406967,"max":0.1039000004529953,"mean":0.09428313765620228,"stDev":0.0026415405130512967}},{"date":"2016-01-11","basicStats":{"min":0.7870000004768372,"max":0.8919000029563904,"mean":0.8328277862404093,"stDev":0.027122696351919603}}],"C7":[{"date":"2016-12-29","basicStats":{"min":0.6833999752998352,"max":1.0740000009536743,"mean":0.8514354847306029,"stDev":0.09042530470452026}},{"date":"2016-12-26","basicStats":{"min":0.15940000116825104,"max":0.25220000743865967,"mean":0.18125674486859453,"stDev":0.015912283963508134}},{"date":"2016-12-19","basicStats":{"min":0.10270000249147415,"max":0.23739999532699585,"mean":0.16848585057096926,"stDev":0.027408623705901546}},{"date":"2016-12-16","basicStats":{"min":0.4390000104904175,"max":0.4902999997138977,"mean":0.4654029327447459,"stDev":0.012529400657745453}},{"date":"2016-12-09","basicStats":{"min":0.7135000228881836,"max":0.7394000291824341,"mean":0.7262245598863653,"stDev":0.006169094617974303}},{"date":"2016-12-06","basicStats":{"min":0.7447999715805054,"max":0.8241000175476074,"mean":0.7919105570599491,"stDev":0.01347700617473547}},{"date":"2016-11-26","basicStats":{"min":0.5127000212669373,"max":0.7820000052452087,"mean":0.6646986805623586,"stDev":0.040606938164661925}},{"date":"2016-11-19","basicStats":{"min":0.16089999675750732,"max":0.17870000004768372,"mean":0.17084186210616595,"stDev":0.003214373942830553}},{"date":"2016-11-16","basicStats":{"min":0.3025999963283539,"max":0.4433000087738037,"mean":0.3601338711520793,"stDev":0.03957721813118327}},{"date":"2016-11-09","basicStats":{"min":0.4318000078201294,"max":0.5019999742507935,"mean":0.46237067421597855,"stDev":0.014114879681173507}},{"date":"2016-11-06","basicStats":{"min":0.1477999985218048,"max":0.1923000067472458,"mean":0.16289017598562575,"stDev":0.008609602573792048}},{"date":"2016-10-27","basicStats":{"min":0.15710000693798065,"max":0.20100000500679016,"mean":0.17153335769068095,"stDev":0.008116955558358228}},{"date":"2016-10-20","basicStats":{"min":0.2662999927997589,"max":0.2985999882221222,"mean":0.28683753702734927,"stDev":0.004355712268477119}},{"date":"2016-10-17","basicStats":{"min":0.14000000059604645,"max":0.18809999525547028,"mean":0.15537734607185433,"stDev":0.008457386972468886}},{"date":"2016-10-07","basicStats":{"min":0.1550000011920929,"max":0.2013999968767166,"mean":0.17182192091674395,"stDev":0.007995695212470646}},{"date":"2016-09-30","basicStats":{"min":0.1678999960422516,"max":0.6941999793052673,"mean":0.45698900295754624,"stDev":0.12258842493314151}},{"date":"2016-09-27","basicStats":{"min":0.16110000014305115,"max":0.20110000669956207,"mean":0.17899604102383626,"stDev":0.007306771682954561}},{"date":"2016-09-17","basicStats":{"min":0.16259999573230743,"max":0.20800000429153442,"mean":0.18842719933373106,"stDev":0.008405100005787028}},{"date":"2016-09-10","basicStats":{"min":0.14380000531673431,"max":0.1835000067949295,"mean":0.16604098234096218,"stDev":0.008861408369986067}},{"date":"2016-09-07","basicStats":{"min":0.148499995470047,"max":0.20919999480247498,"mean":0.1822063051317094,"stDev":0.012772972817150653}},{"date":"2016-08-28","basicStats":{"min":0.14329999685287476,"max":0.20489999651908875,"mean":0.17105938405716203,"stDev":0.012064222323614064}},{"date":"2016-08-21","basicStats":{"min":0.12849999964237213,"max":0.19050000607967377,"mean":0.1566872432980893,"stDev":0.013314058804052814}},{"date":"2016-08-18","basicStats":{"min":0.14139999449253082,"max":0.21729999780654907,"mean":0.1784692081101129,"stDev":0.01677040388146615}},{"date":"2016-08-08","basicStats":{"min":0.14480000734329224,"max":0.2215999960899353,"mean":0.18382082111543555,"stDev":0.017670051158436968}},{"date":"2016-08-01","basicStats":{"min":0.13300000131130219,"max":0.19750000536441803,"mean":0.16493086507024984,"stDev":0.014047990460308284}},{"date":"2016-07-29","basicStats":{"min":0.15160000324249268,"max":0.22100000083446503,"mean":0.1875038122283047,"stDev":0.015069631903089263}},{"date":"2016-07-19","basicStats":{"min":0.15809999406337738,"max":0.23770000040531158,"mean":0.2041023460126693,"stDev":0.015664194127861505}},{"date":"2016-07-12","basicStats":{"min":0.1331000030040741,"max":0.21040000021457672,"mean":0.17892155415020755,"stDev":0.012721627294061389}},{"date":"2016-07-09","basicStats":{"min":0.16509999334812164,"max":0.23479999601840973,"mean":0.1995807917477275,"stDev":0.015272725842157355}},{"date":"2016-06-29","basicStats":{"min":0.19599999487400055,"max":0.24529999494552612,"mean":0.22772397352191373,"stDev":0.007245453829486395}},{"date":"2016-06-22","basicStats":{"min":0.163100004196167,"max":0.22550000250339508,"mean":0.20702785913370897,"stDev":0.009442938017816106}},{"date":"2016-06-19","basicStats":{"min":0.20579999685287476,"max":0.2639000117778778,"mean":0.24459288854840208,"stDev":0.008374788636640346}},{"date":"2016-06-09","basicStats":{"min":0.2054000049829483,"max":0.2459000051021576,"mean":0.23175916412184266,"stDev":0.00531974378528994}},{"date":"2016-06-02","basicStats":{"min":1.020799994468689,"max":1.0534000396728516,"mean":1.0364359233561156,"stDev":0.005984648150342331}},{"date":"2016-05-20","basicStats":{"min":0.188400000333786,"max":0.26910001039505005,"mean":0.23548123194587525,"stDev":0.010273706268795984}},{"date":"2016-05-13","basicStats":{"min":0.14810000360012054,"max":0.21250000596046448,"mean":0.19419024927306738,"stDev":0.011019652624451525}},{"date":"2016-04-23","basicStats":{"min":0.1851000040769577,"max":0.28029999136924744,"mean":0.254077419846201,"stDev":0.01530423050748211}},{"date":"2016-04-10","basicStats":{"min":0.2425999939441681,"max":0.2806999981403351,"mean":0.2687807918752921,"stDev":0.006813226711243221}},{"date":"2016-03-24","basicStats":{"min":0.743399977684021,"max":0.7548999786376953,"mean":0.7497684749340385,"stDev":0.0021537832951856227}},{"date":"2016-03-04","basicStats":{"min":0.1527000069618225,"max":0.17010000348091125,"mean":0.16055190595975716,"stDev":0.0032258265621402504}},{"date":"2016-02-10","basicStats":{"min":0.771399974822998,"max":0.7991999983787537,"mean":0.7850354110652754,"stDev":0.006185249758818257}},{"date":"2016-01-24","basicStats":{"min":0.4729999899864197,"max":0.4918000102043152,"mean":0.48257873926169736,"stDev":0.003370099357347459}},{"date":"2016-01-14","basicStats":{"min":0.09189999848604202,"max":0.12070000171661377,"mean":0.10111847493109288,"stDev":0.0038063627472245975}},{"date":"2016-01-11","basicStats":{"min":0.8073999881744385,"max":0.9075999855995178,"mean":0.8533144430680712,"stDev":0.02722954051873392}}],"C8":[{"date":"2016-12-29","basicStats":{"min":0.6822999715805054,"max":1.0885000228881836,"mean":0.8579924485900188,"stDev":0.09323074387905145}},{"date":"2016-12-26","basicStats":{"min":0.16920000314712524,"max":0.26739999651908875,"mean":0.19205403219788278,"stDev":0.01706196848043257}},{"date":"2016-12-19","basicStats":{"min":0.10520000010728836,"max":0.24549999833106995,"mean":0.17489479466333244,"stDev":0.028956944313554688}},{"date":"2016-12-16","basicStats":{"min":0.44589999318122864,"max":0.4968000054359436,"mean":0.4708283726464619,"stDev":0.012664847881937651}},{"date":"2016-12-09","basicStats":{"min":0.7192999720573425,"max":0.7455999851226807,"mean":0.7316543981214413,"stDev":0.005899754666739426}},{"date":"2016-12-06","basicStats":{"min":0.7419000267982483,"max":0.8335999846458435,"mean":0.7974024194776145,"stDev":0.01463464864962708}},{"date":"2016-11-26","basicStats":{"min":0.5320000052452087,"max":0.7928000092506409,"mean":0.6808657626951893,"stDev":0.04056990474581298}},{"date":"2016-11-19","basicStats":{"min":0.164000004529953,"max":0.18389999866485596,"mean":0.1745404691443592,"stDev":0.003448992066794256}},{"date":"2016-11-16","basicStats":{"min":0.31279999017715454,"max":0.45590001344680786,"mean":0.3720329179704363,"stDev":0.04077361452807179}},{"date":"2016-11-09","basicStats":{"min":0.4429999887943268,"max":0.5072000026702881,"mean":0.47293826959524726,"stDev":0.01440459470204477}},{"date":"2016-11-06","basicStats":{"min":0.16539999842643738,"max":0.21580000221729279,"mean":0.1825118765256797,"stDev":0.008517849328565813}},{"date":"2016-10-27","basicStats":{"min":0.18209999799728394,"max":0.22779999673366547,"mean":0.19631605560391546,"stDev":0.008290107144769908}},{"date":"2016-10-20","basicStats":{"min":0.2957000136375427,"max":0.3328000009059906,"mean":0.31714200853340063,"stDev":0.004672076504554066}},{"date":"2016-10-17","basicStats":{"min":0.22460000216960907,"max":0.2831999957561493,"mean":0.2586233136722072,"stDev":0.010540186050387194}},{"date":"2016-10-07","basicStats":{"min":0.2370000034570694,"max":0.27799999713897705,"mean":0.2631507332701661,"stDev":0.006903440899133402}},{"date":"2016-09-30","basicStats":{"min":0.21089999377727509,"max":0.7250000238418579,"mean":0.5016496338037632,"stDev":0.11631717671884917}},{"date":"2016-09-27","basicStats":{"min":0.2506999969482422,"max":0.2890999913215637,"mean":0.2711574048503053,"stDev":0.005460322889266501}},{"date":"2016-09-17","basicStats":{"min":0.26269999146461487,"max":0.2973000109195709,"mean":0.2778277859048059,"stDev":0.004998812970245885}},{"date":"2016-09-10","basicStats":{"min":0.22689999639987946,"max":0.27059999108314514,"mean":0.24617096757696497,"stDev":0.0073634884450630555}},{"date":"2016-09-07","basicStats":{"min":0.25429999828338623,"max":0.30329999327659607,"mean":0.27712228745659007,"stDev":0.00836544467059086}},{"date":"2016-08-28","basicStats":{"min":0.2434999942779541,"max":0.37369999289512634,"mean":0.30641004388545606,"stDev":0.021196418446408818}},{"date":"2016-08-21","basicStats":{"min":0.23420000076293945,"max":0.35510000586509705,"mean":0.28399413481048785,"stDev":0.022560225419057205}},{"date":"2016-08-18","basicStats":{"min":0.2890999913215637,"max":0.39809998869895935,"mean":0.3260912756678648,"stDev":0.022145452968362126}},{"date":"2016-08-08","basicStats":{"min":0.2912999987602234,"max":0.4011000096797943,"mean":0.33216935483591314,"stDev":0.021231960094813648}},{"date":"2016-08-01","basicStats":{"min":0.2554999887943268,"max":0.367900013923645,"mean":0.2992427416604637,"stDev":0.02225748954994382}},{"date":"2016-07-29","basicStats":{"min":0.29589998722076416,"max":0.39969998598098755,"mean":0.3363665688422417,"stDev":0.021030793312011433}},{"date":"2016-07-19","basicStats":{"min":0.3068999946117401,"max":0.3986000120639801,"mean":0.34595351891258935,"stDev":0.018592794025607675}},{"date":"2016-07-12","basicStats":{"min":0.24160000681877136,"max":0.32749998569488525,"mean":0.2840334311499096,"stDev":0.015352145411181645}},{"date":"2016-07-09","basicStats":{"min":0.2621999979019165,"max":0.35899999737739563,"mean":0.30771136382195946,"stDev":0.0207928072765686}},{"date":"2016-06-29","basicStats":{"min":0.2906000018119812,"max":0.3366999924182892,"mean":0.3090407624403752,"stDev":0.0064805221543587374}},{"date":"2016-06-22","basicStats":{"min":0.22380000352859497,"max":0.2987000048160553,"mean":0.2630560855515017,"stDev":0.011529025534349258}},{"date":"2016-06-19","basicStats":{"min":0.28619998693466187,"max":0.329800009727478,"mean":0.3031063787092913,"stDev":0.0068718196122986245}},{"date":"2016-06-09","basicStats":{"min":0.26989999413490295,"max":0.30869999527931213,"mean":0.28102375379056216,"stDev":0.006037992494525981}},{"date":"2016-06-02","basicStats":{"min":1.0223000049591064,"max":1.0496000051498413,"mean":1.033779104958531,"stDev":0.005962862903899449}},{"date":"2016-05-20","basicStats":{"min":0.24879999458789825,"max":0.322299987077713,"mean":0.2684037392942612,"stDev":0.012994650264202856}},{"date":"2016-05-13","basicStats":{"min":0.2062000036239624,"max":0.2500999867916107,"mean":0.23273607034268973,"stDev":0.006907246793744909}},{"date":"2016-04-23","basicStats":{"min":0.25270000100135803,"max":0.3160000145435333,"mean":0.2935541788678711,"stDev":0.00888888391825235}},{"date":"2016-04-10","basicStats":{"min":0.30660000443458557,"max":0.33869999647140503,"mean":0.32607587953466854,"stDev":0.005836741204018741}},{"date":"2016-03-24","basicStats":{"min":0.7565000057220459,"max":0.7724000215530396,"mean":0.7637296924667986,"stDev":0.002122790219733953}},{"date":"2016-03-04","basicStats":{"min":0.17339999973773956,"max":0.21570000052452087,"mean":0.18067206743875197,"stDev":0.005124969407211648}},{"date":"2016-02-10","basicStats":{"min":0.7878000140190125,"max":0.8147000074386597,"mean":0.8011328440782248,"stDev":0.0061023627277446285}},{"date":"2016-01-24","basicStats":{"min":0.4903999865055084,"max":0.5088000297546387,"mean":0.498890028758483,"stDev":0.003317743540635004}},{"date":"2016-01-14","basicStats":{"min":0.09740000218153,"max":0.15940000116825104,"mean":0.10926524921705477,"stDev":0.007051360198969776}},{"date":"2016-01-11","basicStats":{"min":0.8019999861717224,"max":0.9172000288963318,"mean":0.8607556448042217,"stDev":0.027541680499207515}}],"C9":[{"date":"2016-12-29","basicStats":{"min":0.6919000148773193,"max":1.114799976348877,"mean":0.8768387106506712,"stDev":0.09659855616984443}},{"date":"2016-12-26","basicStats":{"min":0.1784999966621399,"max":0.2773999869823456,"mean":0.20241312327578959,"stDev":0.01803826410142356}},{"date":"2016-12-19","basicStats":{"min":0.10980000346899033,"max":0.257099986076355,"mean":0.18289098228789494,"stDev":0.03015335824777056}},{"date":"2016-12-16","basicStats":{"min":0.45260000228881836,"max":0.507099986076355,"mean":0.4788577713050451,"stDev":0.013217493451199224}},{"date":"2016-12-09","basicStats":{"min":0.7290999889373779,"max":0.7555999755859375,"mean":0.7426615839392559,"stDev":0.005877932181016552}},{"date":"2016-12-06","basicStats":{"min":0.748199999332428,"max":0.8454999923706055,"mean":0.8099760261973337,"stDev":0.015861821182323935}},{"date":"2016-11-26","basicStats":{"min":0.5289999842643738,"max":0.8069999814033508,"mean":0.6966963340460032,"stDev":0.040002852637220226}},{"date":"2016-11-19","basicStats":{"min":0.17020000517368317,"max":0.18889999389648438,"mean":0.1805675950917331,"stDev":0.0036844631217402774}},{"date":"2016-11-16","basicStats":{"min":0.3215000033378601,"max":0.4724000096321106,"mean":0.3868091641283456,"stDev":0.04216589663672418}},{"date":"2016-11-09","basicStats":{"min":0.4611000120639801,"max":0.5221999883651733,"mean":0.48759699379069443,"stDev":0.014786825943145834}},{"date":"2016-11-06","basicStats":{"min":0.18219999969005585,"max":0.23770000040531158,"mean":0.20224215560032804,"stDev":0.008965206518821255}},{"date":"2016-10-27","basicStats":{"min":0.20280000567436218,"max":0.2526000142097473,"mean":0.21768687670924775,"stDev":0.008672441457144756}},{"date":"2016-10-20","basicStats":{"min":0.31839999556541443,"max":0.35600000619888306,"mean":0.3387887095950569,"stDev":0.004872979353540873}},{"date":"2016-10-17","basicStats":{"min":0.2513999938964844,"max":0.3328000009059906,"mean":0.2985433285449605,"stDev":0.013845683844921778}},{"date":"2016-10-07","basicStats":{"min":0.2662999927997589,"max":0.3199999928474426,"mean":0.30111656875466947,"stDev":0.00863837293154936}},{"date":"2016-09-30","basicStats":{"min":0.23770000040531158,"max":0.744700014591217,"mean":0.5361425954072886,"stDev":0.11239212741630614}},{"date":"2016-09-27","basicStats":{"min":0.28279998898506165,"max":0.33570000529289246,"mean":0.3113708945750493,"stDev":0.007345885655662191}},{"date":"2016-09-17","basicStats":{"min":0.29319998621940613,"max":0.34459999203681946,"mean":0.317048900266372,"stDev":0.007162869323336496}},{"date":"2016-09-10","basicStats":{"min":0.2621999979019165,"max":0.3172999918460846,"mean":0.28447265378977904,"stDev":0.010497415116045504}},{"date":"2016-09-07","basicStats":{"min":0.29109999537467957,"max":0.352400004863739,"mean":0.3161542523335506,"stDev":0.01158298116227746}},{"date":"2016-08-28","basicStats":{"min":0.2648000121116638,"max":0.44690001010894775,"mean":0.35342983899315783,"stDev":0.029006247298167923}},{"date":"2016-08-21","basicStats":{"min":0.27459999918937683,"max":0.4327000081539154,"mean":0.3317942082051654,"stDev":0.03138713186968621}},{"date":"2016-08-18","basicStats":{"min":0.3190000057220459,"max":0.4794999957084656,"mean":0.3760016859670187,"stDev":0.03129943710656981}},{"date":"2016-08-08","basicStats":{"min":0.32269999384880066,"max":0.4796999990940094,"mean":0.3823967741425438,"stDev":0.030262511462239503}},{"date":"2016-08-01","basicStats":{"min":0.289000004529953,"max":0.44940000772476196,"mean":0.3484637829259341,"stDev":0.03133518587051488}},{"date":"2016-07-29","basicStats":{"min":0.3287999927997589,"max":0.4830000102519989,"mean":0.3885724342638443,"stDev":0.029524694514978855}},{"date":"2016-07-19","basicStats":{"min":0.33739998936653137,"max":0.4666999876499176,"mean":0.3923944277890966,"stDev":0.024630350126504393}},{"date":"2016-07-12","basicStats":{"min":0.2800000011920929,"max":0.376800000667572,"mean":0.32377785922757296,"stDev":0.019252356234017567}},{"date":"2016-07-09","basicStats":{"min":0.29820001125335693,"max":0.40779998898506165,"mean":0.34718570360078177,"stDev":0.024632994536438527}},{"date":"2016-06-29","basicStats":{"min":0.3174999952316284,"max":0.38359999656677246,"mean":0.3424531525312282,"stDev":0.008963062440455239}},{"date":"2016-06-22","basicStats":{"min":0.241799995303154,"max":0.3366999924182892,"mean":0.2882975808992065,"stDev":0.013920800691803022}},{"date":"2016-06-19","basicStats":{"min":0.3095000088214874,"max":0.3783000111579895,"mean":0.33114420836709463,"stDev":0.009899428954519921}},{"date":"2016-06-09","basicStats":{"min":0.2922999858856201,"max":0.3422999978065491,"mean":0.3053858499984936,"stDev":0.007788618531241675}},{"date":"2016-06-02","basicStats":{"min":1.0219000577926636,"max":1.0532000064849854,"mean":1.0344878294425979,"stDev":0.005710351574923541}},{"date":"2016-05-20","basicStats":{"min":0.2687000036239624,"max":0.3531000018119812,"mean":0.29006781540483245,"stDev":0.014915827456817621}},{"date":"2016-05-13","basicStats":{"min":0.226500004529953,"max":0.28110000491142273,"mean":0.25519692028198077,"stDev":0.007925794247477616}},{"date":"2016-04-23","basicStats":{"min":0.27630001306533813,"max":0.3434999883174896,"mean":0.3184899558856688,"stDev":0.009574663108712031}},{"date":"2016-04-10","basicStats":{"min":0.33149999380111694,"max":0.36399999260902405,"mean":0.3516679616573965,"stDev":0.006215036331746509}},{"date":"2016-03-24","basicStats":{"min":0.7753999829292297,"max":0.7910000085830688,"mean":0.7825361441307395,"stDev":0.0024263257800195698}},{"date":"2016-03-04","basicStats":{"min":0.18520000576972961,"max":0.24220000207424164,"mean":0.19487727299070473,"stDev":0.006484336754919347}},{"date":"2016-02-10","basicStats":{"min":0.7972999811172485,"max":0.8271999955177307,"mean":0.8110390763041556,"stDev":0.005941996753986643}},{"date":"2016-01-24","basicStats":{"min":0.5037999749183655,"max":0.5238000154495239,"mean":0.5124275652456848,"stDev":0.0034094580268139566}},{"date":"2016-01-14","basicStats":{"min":0.10239999741315842,"max":0.17020000517368317,"mean":0.11632859223464906,"stDev":0.008160089142604634}},{"date":"2016-01-11","basicStats":{"min":0.8027999997138977,"max":0.9286999702453613,"mean":0.8746986806043079,"stDev":0.029006561847455255}}],"C10":[{"date":"2016-12-29","basicStats":{"min":0.6854000091552734,"max":1.1131999492645264,"mean":0.8671261719332418,"stDev":0.09764896679199148}},{"date":"2016-12-26","basicStats":{"min":0.17100000381469727,"max":0.24570000171661377,"mean":0.19830337262922731,"stDev":0.01597371815415048}},{"date":"2016-12-19","basicStats":{"min":0.10490000247955322,"max":0.2513999938964844,"mean":0.17783519065231532,"stDev":0.02994886039096683}},{"date":"2016-12-16","basicStats":{"min":0.43810001015663147,"max":0.4927999973297119,"mean":0.4639079911180962,"stDev":0.012020169965417958}},{"date":"2016-12-09","basicStats":{"min":0.7045999765396118,"max":0.7416999936103821,"mean":0.7235376835743362,"stDev":0.007532251856953988}},{"date":"2016-12-06","basicStats":{"min":0.7681000232696533,"max":0.8191999793052673,"mean":0.7919293986387611,"stDev":0.01063013327006179}},{"date":"2016-11-26","basicStats":{"min":0.45890000462532043,"max":0.7885000109672546,"mean":0.6813212610409755,"stDev":0.04532194090084096}},{"date":"2016-11-19","basicStats":{"min":0.16359999775886536,"max":0.1834000051021576,"mean":0.17179736063496132,"stDev":0.003232402016577311}},{"date":"2016-11-16","basicStats":{"min":0.3037000000476837,"max":0.45249998569488525,"mean":0.36124956044109013,"stDev":0.03509074070933191}},{"date":"2016-11-09","basicStats":{"min":0.44179999828338623,"max":0.5152000188827515,"mean":0.4749627567150378,"stDev":0.012112684058994806}},{"date":"2016-11-06","basicStats":{"min":0.1826000064611435,"max":0.23479999601840973,"mean":0.20469824064118788,"stDev":0.009305670575372078}},{"date":"2016-10-27","basicStats":{"min":0.19619999825954437,"max":0.24950000643730164,"mean":0.21421796194881312,"stDev":0.009068672770288078}},{"date":"2016-10-20","basicStats":{"min":0.31700000166893005,"max":0.34279999136924744,"mean":0.33045021999529056,"stDev":0.004780353628597794}},{"date":"2016-10-17","basicStats":{"min":0.23759999871253967,"max":0.3253999948501587,"mean":0.2896197214941124,"stDev":0.01374507636573513}},{"date":"2016-10-07","basicStats":{"min":0.2551000118255615,"max":0.3140999972820282,"mean":0.2930134897751199,"stDev":0.009074741012156698}},{"date":"2016-09-30","basicStats":{"min":0.20960000157356262,"max":0.7493000030517578,"mean":0.47766942785413613,"stDev":0.13184853513970995}},{"date":"2016-09-27","basicStats":{"min":0.267300009727478,"max":0.32659998536109924,"mean":0.30078313720366173,"stDev":0.008223658383121045}},{"date":"2016-09-17","basicStats":{"min":0.2816999852657318,"max":0.33469998836517334,"mean":0.3058758065148184,"stDev":0.009338854913909282}},{"date":"2016-09-10","basicStats":{"min":0.24719999730587006,"max":0.3160000145435333,"mean":0.2769978740129651,"stDev":0.012266755843414825}},{"date":"2016-09-07","basicStats":{"min":0.2773999869823456,"max":0.3531000018119812,"mean":0.3111915688448289,"stDev":0.014073160095993931}},{"date":"2016-08-28","basicStats":{"min":0.24150000512599945,"max":0.4388999938964844,"mean":0.3411546186311853,"stDev":0.03112594470966152}},{"date":"2016-08-21","basicStats":{"min":0.25619998574256897,"max":0.4350000023841858,"mean":0.32152939898090277,"stDev":0.03384857142018193}},{"date":"2016-08-18","basicStats":{"min":0.2971999943256378,"max":0.4699999988079071,"mean":0.3624043989260177,"stDev":0.03365685881632073}},{"date":"2016-08-08","basicStats":{"min":0.3050999939441681,"max":0.47859999537467957,"mean":0.3687376833556335,"stDev":0.03281830961100316}},{"date":"2016-08-01","basicStats":{"min":0.27000001072883606,"max":0.44350001215934753,"mean":0.33536385644303673,"stDev":0.033569179283402875}},{"date":"2016-07-29","basicStats":{"min":0.3025999963283539,"max":0.4659999907016754,"mean":0.368441128813801,"stDev":0.031449878128484876}},{"date":"2016-07-19","basicStats":{"min":0.31310001015663147,"max":0.45410001277923584,"mean":0.37355249272413593,"stDev":0.02626722913922457}},{"date":"2016-07-12","basicStats":{"min":0.25839999318122864,"max":0.3718999922275543,"mean":0.3079485332817275,"stDev":0.020401535606616908}},{"date":"2016-07-09","basicStats":{"min":0.2542000114917755,"max":0.39820000529289246,"mean":0.3259130498924214,"stDev":0.024812844096880195}},{"date":"2016-06-29","basicStats":{"min":0.29809999465942383,"max":0.3702999949455261,"mean":0.3235277859958387,"stDev":0.009423874065990444}},{"date":"2016-06-22","basicStats":{"min":0.2280000001192093,"max":0.33469998836517334,"mean":0.2765264662851158,"stDev":0.014718039726164457}},{"date":"2016-06-19","basicStats":{"min":0.2912999987602234,"max":0.376800000667572,"mean":0.3146752199469428,"stDev":0.011500549638952865}},{"date":"2016-06-09","basicStats":{"min":0.27630001306533813,"max":0.3434999883174896,"mean":0.29187008817174975,"stDev":0.008107143295180015}},{"date":"2016-06-02","basicStats":{"min":0.9958999752998352,"max":1.0298000574111938,"mean":1.0148911291290925,"stDev":0.006293565605353663}},{"date":"2016-05-20","basicStats":{"min":0.2549000084400177,"max":0.34310001134872437,"mean":0.27607228735849615,"stDev":0.015624215190157711}},{"date":"2016-05-13","basicStats":{"min":0.20059999823570251,"max":0.27070000767707825,"mean":0.23967631941229714,"stDev":0.008743360785182935}},{"date":"2016-04-23","basicStats":{"min":0.24979999661445618,"max":0.3337000012397766,"mean":0.3032735337959357,"stDev":0.010547934603688042}},{"date":"2016-04-10","basicStats":{"min":0.30660000443458557,"max":0.34869998693466187,"mean":0.3372166423984633,"stDev":0.007076169851866471}},{"date":"2016-03-24","basicStats":{"min":0.7513999938964844,"max":0.7674999833106995,"mean":0.7595209677285819,"stDev":0.002556246786912028}},{"date":"2016-03-04","basicStats":{"min":0.1695999950170517,"max":0.2290000021457672,"mean":0.18164398824888905,"stDev":0.006041235441720039}},{"date":"2016-02-10","basicStats":{"min":0.7681999802589417,"max":0.7996000051498413,"mean":0.7827042523017725,"stDev":0.0061236712749121285}},{"date":"2016-01-24","basicStats":{"min":0.48829999566078186,"max":0.5115000009536743,"mean":0.5000815978628798,"stDev":0.0037287607443231225}},{"date":"2016-01-14","basicStats":{"min":0.09600000083446503,"max":0.17059999704360962,"mean":0.11076041044465243,"stDev":0.007249005445110489}},{"date":"2016-01-11","basicStats":{"min":0.7957000136375427,"max":0.9174000024795532,"mean":0.841484456948522,"stDev":0.02909084590971566}}],"C11":[{"date":"2016-12-29","basicStats":{"min":0.6894999742507935,"max":1.1318000555038452,"mean":0.882564148289368,"stDev":0.10024629521431655}},{"date":"2016-12-26","basicStats":{"min":0.1834000051021576,"max":0.2870999872684479,"mean":0.21128357792835772,"stDev":0.019596005967298557}},{"date":"2016-12-19","basicStats":{"min":0.11410000175237656,"max":0.2696000039577484,"mean":0.18925447216874677,"stDev":0.031680720936288854}},{"date":"2016-12-16","basicStats":{"min":0.4496999979019165,"max":0.5115000009536743,"mean":0.4791141491044642,"stDev":0.013797305762856657}},{"date":"2016-12-09","basicStats":{"min":0.7289999723434448,"max":0.756600022315979,"mean":0.7420057189429614,"stDev":0.0057653533929915}},{"date":"2016-12-06","basicStats":{"min":0.7458000183105469,"max":0.8436999917030334,"mean":0.8105071847302464,"stDev":0.015973208622908727}},{"date":"2016-11-26","basicStats":{"min":0.5055000185966492,"max":0.8036999702453613,"mean":0.7094478008946368,"stDev":0.03980583926527652}},{"date":"2016-11-19","basicStats":{"min":0.17299999296665192,"max":0.19189999997615814,"mean":0.18271891470135468,"stDev":0.0039166005474631825}},{"date":"2016-11-16","basicStats":{"min":0.32679998874664307,"max":0.48100000619888306,"mean":0.39711678878040946,"stDev":0.04332326859515723}},{"date":"2016-11-09","basicStats":{"min":0.46720001101493835,"max":0.5302000045776367,"mean":0.497432991163122,"stDev":0.01477325184956401}},{"date":"2016-11-06","basicStats":{"min":0.20280000567436218,"max":0.26649999618530273,"mean":0.22786825499838792,"stDev":0.009945436630075202}},{"date":"2016-10-27","basicStats":{"min":0.22020000219345093,"max":0.28290000557899475,"mean":0.24106063030638286,"stDev":0.009724783922235745}},{"date":"2016-10-20","basicStats":{"min":0.33739998936653137,"max":0.3779999911785126,"mean":0.3584881964142369,"stDev":0.005272999729701107}},{"date":"2016-10-17","basicStats":{"min":0.27489998936653137,"max":0.3594000041484833,"mean":0.3293096044502304,"stDev":0.013694247457304182}},{"date":"2016-10-07","basicStats":{"min":0.2921999990940094,"max":0.3481000065803528,"mean":0.3294538122074694,"stDev":0.009044142144496952}},{"date":"2016-09-30","basicStats":{"min":0.25369998812675476,"max":0.7662000060081482,"mean":0.5654667885509755,"stDev":0.10760825421886423}},{"date":"2016-09-27","basicStats":{"min":0.31130000948905945,"max":0.361299991607666,"mean":0.3410956011183803,"stDev":0.00858590200111332}},{"date":"2016-09-17","basicStats":{"min":0.322299987077713,"max":0.3716999888420105,"mean":0.3466964810868163,"stDev":0.009595323888374857}},{"date":"2016-09-10","basicStats":{"min":0.2856999933719635,"max":0.3513999879360199,"mean":0.3124887828340981,"stDev":0.013344299526177179}},{"date":"2016-09-07","basicStats":{"min":0.31209999322891235,"max":0.39559999108314514,"mean":0.3454967006778792,"stDev":0.014475494286425986}},{"date":"2016-08-28","basicStats":{"min":0.28690001368522644,"max":0.4733999967575073,"mean":0.3754552053041822,"stDev":0.031154333274014956}},{"date":"2016-08-21","basicStats":{"min":0.29170000553131104,"max":0.4562999904155731,"mean":0.35069567454525435,"stDev":0.033270916691987146}},{"date":"2016-08-18","basicStats":{"min":0.3310000002384186,"max":0.5077999830245972,"mean":0.3970532991057617,"stDev":0.033408618998308076}},{"date":"2016-08-08","basicStats":{"min":0.3393999934196472,"max":0.5138999819755554,"mean":0.4025470674081638,"stDev":0.03200219930120595}},{"date":"2016-08-01","basicStats":{"min":0.304500013589859,"max":0.4684000015258789,"mean":0.3660805718945966,"stDev":0.032880623641796385}},{"date":"2016-07-29","basicStats":{"min":0.34779998660087585,"max":0.507099986076355,"mean":0.41051019070522565,"stDev":0.03150447381977984}},{"date":"2016-07-19","basicStats":{"min":0.35190001130104065,"max":0.490200012922287,"mean":0.41029736050063254,"stDev":0.02528946226282633}},{"date":"2016-07-12","basicStats":{"min":0.2971999943256378,"max":0.39640000462532043,"mean":0.33877947240456036,"stDev":0.020136171382468895}},{"date":"2016-07-09","basicStats":{"min":0.31369999051094055,"max":0.42800000309944153,"mean":0.3641391491348092,"stDev":0.026199449273585945}},{"date":"2016-06-29","basicStats":{"min":0.337799996137619,"max":0.4025999903678894,"mean":0.35829076208064986,"stDev":0.009653374574015414}},{"date":"2016-06-22","basicStats":{"min":0.2484000027179718,"max":0.3555000126361847,"mean":0.2997696481186275,"stDev":0.015612475577113975}},{"date":"2016-06-19","basicStats":{"min":0.3228999972343445,"max":0.40619999170303345,"mean":0.3457859239358004,"stDev":0.011492972836159927}},{"date":"2016-06-09","basicStats":{"min":0.30399999022483826,"max":0.3644999861717224,"mean":0.31858394461031153,"stDev":0.009243954739829294}},{"date":"2016-06-02","basicStats":{"min":1.0024000406265259,"max":1.030400037765503,"mean":1.014762243567324,"stDev":0.005381158611406005}},{"date":"2016-05-20","basicStats":{"min":0.27869999408721924,"max":0.3677000105381012,"mean":0.3025704544048502,"stDev":0.01636490535159516}},{"date":"2016-05-13","basicStats":{"min":0.23649999499320984,"max":0.2944999933242798,"mean":0.26628350454472666,"stDev":0.008787046236509739}},{"date":"2016-04-23","basicStats":{"min":0.2863999903202057,"max":0.3619999885559082,"mean":0.32998328468055005,"stDev":0.010417207482426883}},{"date":"2016-04-10","basicStats":{"min":0.33570000529289246,"max":0.37369999289512634,"mean":0.35905498554629645,"stDev":0.0067477514862798234}},{"date":"2016-03-24","basicStats":{"min":0.7770000100135803,"max":0.795199990272522,"mean":0.7866172292365359,"stDev":0.0030724370154082154}},{"date":"2016-03-04","basicStats":{"min":0.18940000236034393,"max":0.25369998812675476,"mean":0.20004772722633718,"stDev":0.00750932267826527}},{"date":"2016-02-10","basicStats":{"min":0.7908999919891357,"max":0.8216999769210815,"mean":0.806635776616612,"stDev":0.00628157600328114}},{"date":"2016-01-24","basicStats":{"min":0.5088000297546387,"max":0.5299000144004822,"mean":0.517636876520524,"stDev":0.003783310763300495}},{"date":"2016-01-14","basicStats":{"min":0.10100000351667404,"max":0.17710000276565552,"mean":0.11787434021158485,"stDev":0.009354038659649734}},{"date":"2016-01-11","basicStats":{"min":0.7936999797821045,"max":0.9319999814033508,"mean":0.8737550582354368,"stDev":0.03149611588580933}}],"C12":[{"date":"2016-12-29","basicStats":{"min":0.2777999937534332,"max":0.47749999165534973,"mean":0.36301195005342735,"stDev":0.046876266586254614}},{"date":"2016-12-26","basicStats":{"min":0.09759999811649323,"max":0.15610000491142273,"mean":0.11315931078822192,"stDev":0.013243511356431441}},{"date":"2016-12-19","basicStats":{"min":0.06440000236034393,"max":0.12160000205039978,"mean":0.09075051323234855,"stDev":0.013420905749686818}},{"date":"2016-12-16","basicStats":{"min":0.23819999396800995,"max":0.26980000734329224,"mean":0.25272082109168154,"stDev":0.008583909090120941}},{"date":"2016-12-09","basicStats":{"min":0.5582000017166138,"max":0.5788999795913696,"mean":0.5685719936823912,"stDev":0.0052717872655203375}},{"date":"2016-12-06","basicStats":{"min":0.5593000054359436,"max":0.6545000076293945,"mean":0.608376246306204,"stDev":0.022112135491293552}},{"date":"2016-11-26","basicStats":{"min":0.320499986410141,"max":0.39989998936653137,"mean":0.36258775609766625,"stDev":0.014136896064930213}},{"date":"2016-11-19","basicStats":{"min":0.06800000369548798,"max":0.07919999957084656,"mean":0.0743116569921068,"stDev":0.0026118196522383545}},{"date":"2016-11-16","basicStats":{"min":0.19269999861717224,"max":0.3059000074863434,"mean":0.24796458978282407,"stDev":0.03278979180772727}},{"date":"2016-11-09","basicStats":{"min":0.30149999260902405,"max":0.3571000099182129,"mean":0.32632118771590124,"stDev":0.015155971547325177}},{"date":"2016-11-06","basicStats":{"min":0.0997999981045723,"max":0.12309999763965607,"mean":0.10876414958726266,"stDev":0.004339493063048901}},{"date":"2016-10-27","basicStats":{"min":0.08510000258684158,"max":0.1006999984383583,"mean":0.09076187692451518,"stDev":0.003485935004113564}},{"date":"2016-10-20","basicStats":{"min":0.15850000083446503,"max":0.17649999260902405,"mean":0.1675678152274173,"stDev":0.0029075767007431903}},{"date":"2016-10-17","basicStats":{"min":0.08150000125169754,"max":0.09449999779462814,"mean":0.08956854846710864,"stDev":0.0026655261760099103}},{"date":"2016-10-07","basicStats":{"min":0.09369999915361404,"max":0.10379999876022339,"mean":0.09954215533201123,"stDev":0.0019778438472903845}},{"date":"2016-09-30","basicStats":{"min":0.08609999716281891,"max":0.4546999931335449,"mean":0.2994513928759132,"stDev":0.0709887188855826}},{"date":"2016-09-27","basicStats":{"min":0.08669999986886978,"max":0.09399999678134918,"mean":0.0909868768495549,"stDev":0.0015322713475834039}},{"date":"2016-09-17","basicStats":{"min":0.08789999783039093,"max":0.09560000151395798,"mean":0.09095021984553572,"stDev":0.0017995622708710914}},{"date":"2016-09-10","basicStats":{"min":0.07760000228881836,"max":0.08780000358819962,"mean":0.08212214071970002,"stDev":0.0023069117561370493}},{"date":"2016-09-07","basicStats":{"min":0.11309999972581863,"max":0.1273999959230423,"mean":0.1187202345710959,"stDev":0.0031180303129992857}},{"date":"2016-08-28","basicStats":{"min":0.09960000216960907,"max":0.12359999865293503,"mean":0.11137375358459352,"stDev":0.005861747934662311}},{"date":"2016-08-21","basicStats":{"min":0.09799999743700027,"max":0.12409999966621399,"mean":0.10943914941700503,"stDev":0.006878197109416501}},{"date":"2016-08-18","basicStats":{"min":0.10909999907016754,"max":0.1324000060558319,"mean":0.11925051324724988,"stDev":0.005159871694489623}},{"date":"2016-08-08","basicStats":{"min":0.11140000075101852,"max":0.13940000534057617,"mean":0.12487023480542406,"stDev":0.006296930327736783}},{"date":"2016-08-01","basicStats":{"min":0.10019999742507935,"max":0.12309999763965607,"mean":0.10918695018613102,"stDev":0.0057841035922292705}},{"date":"2016-07-29","basicStats":{"min":0.08569999784231186,"max":0.1054999977350235,"mean":0.09387434019414907,"stDev":0.004623981456563358}},{"date":"2016-07-19","basicStats":{"min":0.10199999809265137,"max":0.12370000034570694,"mean":0.11257404679448885,"stDev":0.004184442669562607}},{"date":"2016-07-12","basicStats":{"min":0.08590000122785568,"max":0.10419999808073044,"mean":0.09496832835621839,"stDev":0.003846696719514131}},{"date":"2016-07-09","basicStats":{"min":0.07590000331401825,"max":0.09269999712705612,"mean":0.08393108505001859,"stDev":0.004430551028574162}},{"date":"2016-06-29","basicStats":{"min":0.09600000083446503,"max":0.1062999963760376,"mean":0.09957859243465642,"stDev":0.0020667126948116215}},{"date":"2016-06-22","basicStats":{"min":0.09529999643564224,"max":0.11729999631643295,"mean":0.10611216995941591,"stDev":0.0042224019707346044}},{"date":"2016-06-19","basicStats":{"min":0.10279999673366547,"max":0.11460000276565552,"mean":0.1081564515785388,"stDev":0.002667249047088581}},{"date":"2016-06-09","basicStats":{"min":0.10360000282526016,"max":0.12200000137090683,"mean":0.10869230192886596,"stDev":0.0032484655065358773}},{"date":"2016-06-02","basicStats":{"min":0.8769999742507935,"max":0.8974999785423279,"mean":0.8879000741190909,"stDev":0.0037689997049965055}},{"date":"2016-05-20","basicStats":{"min":0.08290000259876251,"max":0.10119999945163727,"mean":0.08927390027430748,"stDev":0.004413244052346773}},{"date":"2016-05-13","basicStats":{"min":0.06210000067949295,"max":0.07360000163316727,"mean":0.06721664233750446,"stDev":0.0018405365100081937}},{"date":"2016-04-23","basicStats":{"min":0.09589999914169312,"max":0.1120000034570694,"mean":0.1045337242519488,"stDev":0.0030246141955990328}},{"date":"2016-04-10","basicStats":{"min":0.16869999468326569,"max":0.18389999866485596,"mean":0.17778804972549325,"stDev":0.0027192045679684286}},{"date":"2016-03-24","basicStats":{"min":0.47589999437332153,"max":0.4878000020980835,"mean":0.4829884163401693,"stDev":0.002151038475326438}},{"date":"2016-03-04","basicStats":{"min":0.049800001084804535,"max":0.06210000067949295,"mean":0.05328680352851352,"stDev":0.0024361558018062114}},{"date":"2016-02-10","basicStats":{"min":0.44020000100135803,"max":0.4778999984264374,"mean":0.45718599707325186,"stDev":0.008173813863323158}},{"date":"2016-01-24","basicStats":{"min":0.38359999656677246,"max":0.39890000224113464,"mean":0.3886600441553381,"stDev":0.0032102987187009537}},{"date":"2016-01-14","basicStats":{"min":0.04650000110268593,"max":0.07360000163316727,"mean":0.05399882704664096,"stDev":0.005192431809818465}},{"date":"2016-01-11","basicStats":{"min":0.5372999906539917,"max":0.7447999715805054,"mean":0.6613690617584426,"stDev":0.05159783038983922}}],"C13":[{"date":"2016-12-29","basicStats":{"min":0.42730000615119934,"max":0.8698999881744385,"mean":0.609576099254519,"stDev":0.10082445382623705}},{"date":"2016-12-26","basicStats":{"min":0.16249999403953552,"max":0.24799999594688416,"mean":0.1837208211706009,"stDev":0.01624003529170904}},{"date":"2016-12-19","basicStats":{"min":0.10080000013113022,"max":0.2662999927997589,"mean":0.18348284458463,"stDev":0.034645695699165466}},{"date":"2016-12-16","basicStats":{"min":0.12759999930858612,"max":0.15760000050067902,"mean":0.13921928177437468,"stDev":0.006227179063424158}},{"date":"2016-12-09","basicStats":{"min":0.1995999962091446,"max":0.21940000355243683,"mean":0.2087504400317272,"stDev":0.005171998318556311}},{"date":"2016-12-06","basicStats":{"min":0.22579999268054962,"max":0.27410000562667847,"mean":0.24830887093047588,"stDev":0.012960957355839688}},{"date":"2016-11-26","basicStats":{"min":0.06920000165700912,"max":0.10320000350475311,"mean":0.08593643697585007,"stDev":0.006078702989052643}},{"date":"2016-11-19","basicStats":{"min":0.07100000232458115,"max":0.08370000123977661,"mean":0.0783334311065087,"stDev":0.0023700594268012904}},{"date":"2016-11-16","basicStats":{"min":0.1972000002861023,"max":0.3386000096797943,"mean":0.25443834290345385,"stDev":0.04022907890572955}},{"date":"2016-11-09","basicStats":{"min":0.23569999635219574,"max":0.2623000144958496,"mean":0.2469353368314656,"stDev":0.005764816705039373}},{"date":"2016-11-06","basicStats":{"min":0.19820000231266022,"max":0.25859999656677246,"mean":0.21834288867425375,"stDev":0.01201944346868923}},{"date":"2016-10-27","basicStats":{"min":0.2184000015258789,"max":0.28290000557899475,"mean":0.2401231672297997,"stDev":0.012728717920292407}},{"date":"2016-10-20","basicStats":{"min":0.2345999926328659,"max":0.27619999647140503,"mean":0.25876796172380095,"stDev":0.005299216564341399}},{"date":"2016-10-17","basicStats":{"min":0.18039999902248383,"max":0.26350000500679016,"mean":0.20017727273256908,"stDev":0.01486283172569815}},{"date":"2016-10-07","basicStats":{"min":0.20180000364780426,"max":0.26570001244544983,"mean":0.2233524194364149,"stDev":0.012126781589896}},{"date":"2016-09-30","basicStats":{"min":0.17489999532699585,"max":0.75,"mean":0.5249564520512162,"stDev":0.12647541864165174}},{"date":"2016-09-27","basicStats":{"min":0.2092999964952469,"max":0.26339998841285706,"mean":0.2342875363234201,"stDev":0.010096555355091618}},{"date":"2016-09-17","basicStats":{"min":0.2175000011920929,"max":0.26989999413490295,"mean":0.24354706733020542,"stDev":0.01026170801107919}},{"date":"2016-09-10","basicStats":{"min":0.18559999763965607,"max":0.2409999966621399,"mean":0.21328269776579584,"stDev":0.011337043023948664}},{"date":"2016-09-07","basicStats":{"min":0.19709999859333038,"max":0.26820001006126404,"mean":0.23524486802278033,"stDev":0.015502153245145261}},{"date":"2016-08-28","basicStats":{"min":0.1843000054359436,"max":0.2599000036716461,"mean":0.21637881220566907,"stDev":0.01662482629634081}},{"date":"2016-08-21","basicStats":{"min":0.16609999537467957,"max":0.24480000138282776,"mean":0.1983925951562844,"stDev":0.01801114267102456}},{"date":"2016-08-18","basicStats":{"min":0.19689999520778656,"max":0.2816999852657318,"mean":0.23423577731480696,"stDev":0.020510826132059106}},{"date":"2016-08-08","basicStats":{"min":0.20200000703334808,"max":0.2883000075817108,"mean":0.24524362158041185,"stDev":0.020706004371024465}},{"date":"2016-08-01","basicStats":{"min":0.18719999492168427,"max":0.25589999556541443,"mean":0.2195790322972709,"stDev":0.01689572942716186}},{"date":"2016-07-29","basicStats":{"min":0.21889999508857727,"max":0.2964000105857849,"mean":0.26016290354763644,"stDev":0.01838772904999546}},{"date":"2016-07-19","basicStats":{"min":0.22550000250339508,"max":0.3140999972820282,"mean":0.27885960393156467,"stDev":0.016815907376677503}},{"date":"2016-07-12","basicStats":{"min":0.18649999797344208,"max":0.2721000015735626,"mean":0.24008900301853217,"stDev":0.016671413213557435}},{"date":"2016-07-09","basicStats":{"min":0.21709999442100525,"max":0.3174999952316284,"mean":0.27188922255095094,"stDev":0.022979273506522468}},{"date":"2016-06-29","basicStats":{"min":0.27300000190734863,"max":0.320499986410141,"mean":0.30553944293092744,"stDev":0.007871328853126226}},{"date":"2016-06-22","basicStats":{"min":0.2085999995470047,"max":0.29919999837875366,"mean":0.2735235339516775,"stDev":0.016564003304633697}},{"date":"2016-06-19","basicStats":{"min":0.2849000096321106,"max":0.34950000047683716,"mean":0.33087763963731504,"stDev":0.009316698861829864}},{"date":"2016-06-09","basicStats":{"min":0.2809000015258789,"max":0.325300008058548,"mean":0.3072068913897109,"stDev":0.006328738575724183}},{"date":"2016-06-02","basicStats":{"min":0.18019999563694,"max":0.21130000054836273,"mean":0.20003277126732472,"stDev":0.00737579092377919}},{"date":"2016-05-20","basicStats":{"min":0.2784000039100647,"max":0.3495999872684479,"mean":0.3174440613852221,"stDev":0.011838777668553279}},{"date":"2016-05-13","basicStats":{"min":0.20640000700950623,"max":0.28380000591278076,"mean":0.25943086487500594,"stDev":0.012721305344468817}},{"date":"2016-04-23","basicStats":{"min":0.2540000081062317,"max":0.37400001287460327,"mean":0.33546136358965883,"stDev":0.020438681740470813}},{"date":"2016-04-10","basicStats":{"min":0.1559000015258789,"max":0.19670000672340393,"mean":0.18472668613768717,"stDev":0.007753430335394317}},{"date":"2016-03-24","basicStats":{"min":0.25220000743865967,"max":0.2599000036716461,"mean":0.256334677032711,"stDev":0.001412457704268735}},{"date":"2016-03-04","basicStats":{"min":0.19550000131130219,"max":0.22699999809265137,"mean":0.20882360710382802,"stDev":0.006937990801740762}},{"date":"2016-02-10","basicStats":{"min":0.22669999301433563,"max":0.2535000145435333,"mean":0.23788497039824277,"stDev":0.0060142389301617106}},{"date":"2016-01-24","basicStats":{"min":0.23100000619888306,"max":0.2402999997138977,"mean":0.23535828434389708,"stDev":0.0014821212560389976}},{"date":"2016-01-14","basicStats":{"min":0.0997999981045723,"max":0.14970000088214874,"mean":0.11721473596880853,"stDev":0.007675041187644877}},{"date":"2016-01-11","basicStats":{"min":0.2727000117301941,"max":0.39079999923706055,"mean":0.337658064827716,"stDev":0.027360526806284882}}],"C14":[{"date":"2016-12-29","basicStats":{"min":0.2687000036239624,"max":0.6672999858856201,"mean":0.4372051321516285,"stDev":0.0888687127992659}},{"date":"2016-12-26","basicStats":{"min":0.13120000064373016,"max":0.23720000684261322,"mean":0.15894281525503529,"stDev":0.021837691608177074}},{"date":"2016-12-19","basicStats":{"min":0.07639999687671661,"max":0.24940000474452972,"mean":0.163398167151204,"stDev":0.036546234638440034}},{"date":"2016-12-16","basicStats":{"min":0.12700000405311584,"max":0.16050000488758087,"mean":0.13935989731392898,"stDev":0.006882190355928919}},{"date":"2016-12-09","basicStats":{"min":0.225600004196167,"max":0.24449999630451202,"mean":0.23326913468386765,"stDev":0.004641490890365738}},{"date":"2016-12-06","basicStats":{"min":0.25029999017715454,"max":0.3052999973297119,"mean":0.2770359234725969,"stDev":0.013814449922815475}},{"date":"2016-11-26","basicStats":{"min":0.06319999694824219,"max":0.10320000350475311,"mean":0.08083797664630094,"stDev":0.006678642267859748}},{"date":"2016-11-19","basicStats":{"min":0.05959999933838844,"max":0.07190000265836716,"mean":0.06664186229934778,"stDev":0.002458881829197292}},{"date":"2016-11-16","basicStats":{"min":0.18440000712871552,"max":0.3361000120639801,"mean":0.2480237535979391,"stDev":0.04433847185253313}},{"date":"2016-11-09","basicStats":{"min":0.23849999904632568,"max":0.2680000066757202,"mean":0.2515199409573835,"stDev":0.007017753744196602}},{"date":"2016-11-06","basicStats":{"min":0.1444000005722046,"max":0.20340000092983246,"mean":0.16435799116263308,"stDev":0.010734378247427939}},{"date":"2016-10-27","basicStats":{"min":0.16369999945163727,"max":0.22709999978542328,"mean":0.18402932553696852,"stDev":0.011795388139860427}},{"date":"2016-10-20","basicStats":{"min":0.1842000037431717,"max":0.23810000717639923,"mean":0.21520659825669017,"stDev":0.0072671671330876205}},{"date":"2016-10-17","basicStats":{"min":0.10369999706745148,"max":0.179299995303154,"mean":0.12311026382961933,"stDev":0.013747752035000064}},{"date":"2016-10-07","basicStats":{"min":0.12449999898672104,"max":0.18860000371932983,"mean":0.14702272730336,"stDev":0.01169353639168767}},{"date":"2016-09-30","basicStats":{"min":0.12099999934434891,"max":0.6373000144958496,"mean":0.4427983142173356,"stDev":0.10933599351848819}},{"date":"2016-09-27","basicStats":{"min":0.12639999389648438,"max":0.18299999833106995,"mean":0.15379318168872957,"stDev":0.010305291608377756}},{"date":"2016-09-17","basicStats":{"min":0.13189999759197235,"max":0.1881999969482422,"mean":0.16243042498608493,"stDev":0.012027271717926084}},{"date":"2016-09-10","basicStats":{"min":0.10180000215768814,"max":0.16910000145435333,"mean":0.13788357755043634,"stDev":0.0140007883053681}},{"date":"2016-09-07","basicStats":{"min":0.10649999976158142,"max":0.20469999313354492,"mean":0.15944002940158364,"stDev":0.020131531779432003}},{"date":"2016-08-28","basicStats":{"min":0.09239999949932098,"max":0.19539999961853027,"mean":0.14021290326900673,"stDev":0.022707383135390433}},{"date":"2016-08-21","basicStats":{"min":0.07999999821186066,"max":0.18160000443458557,"mean":0.12567837242463142,"stDev":0.023949582441258225}},{"date":"2016-08-18","basicStats":{"min":0.09759999811649323,"max":0.21439999341964722,"mean":0.15417008785820416,"stDev":0.028191142721073707}},{"date":"2016-08-08","basicStats":{"min":0.10300000011920929,"max":0.22190000116825104,"mean":0.16369545474495528,"stDev":0.029013474745735637}},{"date":"2016-08-01","basicStats":{"min":0.09350000321865082,"max":0.19020000100135803,"mean":0.14047991206372393,"stDev":0.024641459110184925}},{"date":"2016-07-29","basicStats":{"min":0.11670000106096268,"max":0.2264000028371811,"mean":0.1714490469807316,"stDev":0.0275544583407466}},{"date":"2016-07-19","basicStats":{"min":0.12700000405311584,"max":0.24390000104904175,"mean":0.19312727277623218,"stDev":0.025118077427329993}},{"date":"2016-07-12","basicStats":{"min":0.10490000247955322,"max":0.2093999981880188,"mean":0.16468812313335016,"stDev":0.020188561880634507}},{"date":"2016-07-09","basicStats":{"min":0.13300000131130219,"max":0.2443999946117401,"mean":0.19230351907329463,"stDev":0.023513185740116724}},{"date":"2016-06-29","basicStats":{"min":0.19130000472068787,"max":0.26030001044273376,"mean":0.2376474337297274,"stDev":0.012091792054425956}},{"date":"2016-06-22","basicStats":{"min":0.15839999914169312,"max":0.24719999730587006,"mean":0.2202942083177327,"stDev":0.01788831029424343}},{"date":"2016-06-19","basicStats":{"min":0.20160000026226044,"max":0.2985000014305115,"mean":0.2752703075403692,"stDev":0.015697277124105624}},{"date":"2016-06-09","basicStats":{"min":0.211899995803833,"max":0.27639999985694885,"mean":0.25597346040947294,"stDev":0.00880597892990271}},{"date":"2016-06-02","basicStats":{"min":0.21809999644756317,"max":0.251800000667572,"mean":0.2396304987130623,"stDev":0.006557761182116349}},{"date":"2016-05-20","basicStats":{"min":0.22169999778270721,"max":0.30649998784065247,"mean":0.2759948678074346,"stDev":0.012095695834982507}},{"date":"2016-05-13","basicStats":{"min":0.1331000030040741,"max":0.22669999301433563,"mean":0.20434692079239566,"stDev":0.016205647960556426}},{"date":"2016-04-23","basicStats":{"min":0.19249999523162842,"max":0.32499998807907104,"mean":0.2853134896529735,"stDev":0.02436981661897697}},{"date":"2016-04-10","basicStats":{"min":0.13439999520778656,"max":0.17649999260902405,"mean":0.1642296919025635,"stDev":0.00786896837511032}},{"date":"2016-03-24","basicStats":{"min":0.272599995136261,"max":0.28110000491142273,"mean":0.2777722138813158,"stDev":0.0015939726655577813}},{"date":"2016-03-04","basicStats":{"min":0.1518000066280365,"max":0.19779999554157257,"mean":0.17892118761878542,"stDev":0.006818618868827999}},{"date":"2016-02-10","basicStats":{"min":0.24009999632835388,"max":0.26249998807907104,"mean":0.24976019022707666,"stDev":0.005018016680254257}},{"date":"2016-01-24","basicStats":{"min":0.23980000615119934,"max":0.24979999661445618,"mean":0.24448731653064568,"stDev":0.0016433483491533874}},{"date":"2016-01-14","basicStats":{"min":0.0778999999165535,"max":0.10679999738931656,"mean":0.0909663490470379,"stDev":0.005084246698465093}},{"date":"2016-01-11","basicStats":{"min":0.2615000009536743,"max":0.4115000069141388,"mean":0.35491979493598436,"stDev":0.03620071580608296}}]}