{
    "headers": {
        "Content-Type": "application/json",
        "User-Agent": "sentinelhub-py/v3.3.1"
    },
    "payload": {
        "crs": "EPSG:4326",
        "geometry": "POLYGON ((38.79816142580218 65.84957916283591, 38.79774471414646 65.85024487228863, 38.79517144834143 65.84707198063717, 38.79560837995713 65.84635834470224, 38.79816142580218 65.84957916283591))",
        "layer": "AGRICULTURE_L2A",
        "maxcc": 100.0,
        "resolution": "10m",
        "service": "fis",
        "time": "2016-01-01T00:00:00Z/2016-12-30T23:59:59Z",
        "warnings": false
    },
    "timestamp": "2021-07-14T15:59:46.319458",
    "url": "https://services.sentinel-hub.com/ogc/fis/5e98cacf-5c35-4e3b-9674-52c8241a01f1"
}