{
    "headers": {
        "Content-Type": "application/json",
        "User-Agent": "sentinelhub-py/v3.3.1"
    },
    "payload": {
        "crs": "EPSG:4326",
        "geometry": "POLYGON ((40.53911007900007 71.42220598900251, 40.53951775300003 71.4262936760025, 40.53790334800004 71.4265618970025, 40.53740597300002 71.42292482100245, 40.53911007900007 71.42220598900251))",
        "layer": "AGRICULTURE_L2A",
        "maxcc": 100.0,
        "resolution": "10m",
        "service": "fis",
        "time": "2016-01-01T00:00:00Z/2016-12-30T23:59:59Z",
        "warnings": false
    },
    "timestamp": "2021-07-14T14:03:52.002260",
    "url": "https://services.sentinel-hub.com/ogc/fis/5e98cacf-5c35-4e3b-9674-52c8241a01f1"
}