{
    "headers": {
        "Content-Type": "application/json",
        "User-Agent": "sentinelhub-py/v3.3.1"
    },
    "payload": {
        "crs": "EPSG:4326",
        "geometry": "POLYGON ((39.87193144552823 64.24753583728334, 39.87215445486804 64.24807818864919, 39.87250391274113 64.25082249666222, 39.87058645470074 64.25156726931887, 39.87193144552823 64.24753583728334))",
        "layer": "AGRICULTURE_L1C",
        "maxcc": 100.0,
        "resolution": "10m",
        "service": "fis",
        "time": "2016-01-01T00:00:00Z/2016-12-30T23:59:59Z",
        "warnings": false
    },
    "timestamp": "2021-07-14T19:58:09.355541",
    "url": "https://services.sentinel-hub.com/ogc/fis/5e98cacf-5c35-4e3b-9674-52c8241a01f1"
}